Workbook

Sheet Extended P&L
B2: Income statement
C3: Reported | I3: Adjustments | O3: Actuals
B4: Currency: [Insert currency unit e.g, EUR M or USD millions) | C4: 2019 | D4: =C4+1 -> 2020 | E4: =D4+1 -> 2021 | F4: =E4+1 -> 2022 | G4: =F4+1 -> 2023 | I4: 2019 | J4: =I4+1 -> 2020 | K4: =J4+1 -> 2021 | L4: =K4+1 -> 2022 | M4: =L4+1 -> 2023 | O4: 2019 | P4: =O4+1 -> 2020 | Q4: =P4+1 -> 2021 | R4: =Q4+1 -> 2022 | S4: =R4+1 -> 2023
B6: Revenues | C6: ='Revenue breakdown'!C17 -> 651 | D6: ='Revenue breakdown'!D17 -> 572 | E6: ='Revenue breakdown'!E17 -> 615 | F6: ='Revenue breakdown'!F17 -> 469 | G6: ='Revenue breakdown'!G17 -> 540 | I6: 10 | M6: 20 | O6: =C6+I6 -> 661 | P6: =D6+J6 -> 572 | Q6: =E6+K6 -> 615 | R6: =F6+L6 -> 469 | S6: =G6+M6 -> 560
B7: Other income | C7: 0 | D7: 0 | E7: 0 | F7: 0 | G7: 0 | J7: 100 | O7: =C7+I7 -> 0 | P7: =D7+J7 -> 100 | Q7: =E7+K7 -> 0 | R7: =F7+L7 -> 0 | S7: =G7+M7 -> 0
B8: Total revenues | C8: =SUM(C7,C6) -> 651 | D8: =SUM(D7,D6) -> 572 | E8: =SUM(E7,E6) -> 615 | F8: =SUM(F7,F6) -> 469 | G8: =SUM(G7,G6) -> 540 | I8: =SUM(I7,I6) -> 10 | J8: =SUM(J7,J6) -> 100 | K8: =SUM(K7,K6) -> 0 | L8: =SUM(L7,L6) -> 0 | M8: =SUM(M7,M6) -> 20 | O8: =SUM(O7,O6) -> 661 | P8: =SUM(P7,P6) -> 672 | Q8: =SUM(Q7,Q6) -> 615 | R8: =SUM(R7,R6) -> 469 | S8: =SUM(S7,S6) -> 560
B10: COGS (cost of goods sold) | C10: =-'Cost of good sold breakdown'!C13 -> -61 | D10: =-'Cost of good sold breakdown'!D13 -> -55 | E10: =-'Cost of good sold breakdown'!E13 -> -44 | F10: =-'Cost of good sold breakdown'!F13 -> -70 | G10: =-'Cost of good sold breakdown'!G13 -> -67 | M10: -10 | O10: =C10+I10 -> -61 | P10: =D10+J10 -> -55 | Q10: =E10+K10 -> -44 | R10: =F10+L10 -> -70 | S10: =G10+M10 -> -77
B11: Gross margin | C11: =C8+C10 -> 590 | D11: =D8+D10 -> 517 | E11: =E8+E10 -> 571 | F11: =F8+F10 -> 399 | G11: =G8+G10 -> 473 | I11: =I8+I10 -> 10 | J11: =J8+J10 -> 100 | K11: =K8+K10 -> 0 | L11: =L8+L10 -> 0 | M11: =M8+M10 -> 10 | O11: =O8+O10 -> 600 | P11: =P8+P10 -> 617 | Q11: =Q8+Q10 -> 571 | R11: =R8+R10 -> 399 | S11: =S8+S10 -> 483
B13: Salaries | C13: =-'Operating expenses breakdown'!$C$9 -> -23 | D13: =-'Operating expenses breakdown'!$C$9 -> -23 | E13: =-'Operating expenses breakdown'!$C$9 -> -23 | F13: =-'Operating expenses breakdown'!$C$9 -> -23 | G13: =-'Operating expenses breakdown'!$C$9 -> -23 | O13: =C13+I13 -> -23 | P13: =D13+J13 -> -23 | Q13: =E13+K13 -> -23 | R13: =F13+L13 -> -23 | S13: =G13+M13 -> -23
B14: SG&A (selling, general, and administration costs) | C14: =-('Operating expenses breakdown'!$C$14+'Operating expenses breakdown'!$C$20+'Operating expenses breakdown'!$C$25) -> -66 | D14: =-('Operating expenses breakdown'!$C$14+'Operating expenses breakdown'!$C$20+'Operating expenses breakdown'!$C$25) -> -66 | E14: =-('Operating expenses breakdown'!$C$14+'Operating expenses breakdown'!$C$20+'Operating expenses breakdown'!$C$25) -> -66 | F14: =-('Operating expenses breakdown'!$C$14+'Operating expenses breakdown'!$C$20+'Operating expenses breakdown'!$C$25) -> -66 | G14: =-('Operating expenses breakdown'!$C$14+'Operating expenses breakdown'!$C$20+'Operating expenses breakdown'!$C$25) -> -66 | J14: -50 | O14: =C14+I14 -> -66 | P14: =D14+J14 -> -116 | Q14: =E14+K14 -> -66 | R14: =F14+L14 -> -66 | S14: =G14+M14 -> -66
B15: Other costs | C15: =-'Operating expenses breakdown'!$C$27 -> -7 | D15: =-'Operating expenses breakdown'!$C$27 -> -7 | E15: =-'Operating expenses breakdown'!$C$27 -> -7 | F15: =-'Operating expenses breakdown'!$C$27 -> -7 | G15: =-'Operating expenses breakdown'!$C$27 -> -7 | O15: =C15+I15 -> -7 | P15: =D15+J15 -> -7 | Q15: =E15+K15 -> -7 | R15: =F15+L15 -> -7 | S15: =G15+M15 -> -7
B16: Total operating expenses | C16: =SUM(C13:C15) -> -96 | D16: =SUM(D13:D15) -> -96 | E16: =SUM(E13:E15) -> -96 | F16: =SUM(F13:F15) -> -96 | G16: =SUM(G13:G15) -> -96 | I16: =SUM(I13:I15) -> 0 | J16: =SUM(J13:J15) -> -50 | K16: =SUM(K13:K15) -> 0 | L16: =SUM(L13:L15) -> 0 | M16: =SUM(M13:M15) -> 0 | O16: =SUM(O13:O15) -> -96 | P16: =SUM(P13:P15) -> -146 | Q16: =SUM(Q13:Q15) -> -96 | R16: =SUM(R13:R15) -> -96 | S16: =SUM(S13:S15) -> -96
B18: EBITDA | C18: =C11+C16 -> 494 | D18: =D11+D16 -> 421 | E18: =E11+E16 -> 475 | F18: =F11+F16 -> 303 | G18: =G11+G16 -> 377 | I18: =I11+I13+I14+I15 -> 10 | J18: =J11+J13+J14+J15 -> 50 | K18: =K11+K13+K14+K15 -> 0 | L18: =L11+L13+L14+L15 -> 0 | M18: =M11+M13+M14+M15 -> 10 | O18: =O11+O16 -> 504 | P18: =P11+P16 -> 471 | Q18: =Q11+Q16 -> 475 | R18: =R11+R16 -> 303 | S18: =S11+S16 -> 387
B20: Depreciation and amortization | C20: -10 | D20: -10 | E20: -10 | F20: -10 | G20: -10 | O20: =C20+I20 -> -10 | P20: =D20+J20 -> -10 | Q20: =E20+K20 -> -10 | R20: =F20+L20 -> -10 | S20: =G20+M20 -> -10
B21: Operating income (EBIT) | C21: =C18+C20 -> 484 | D21: =D18+D20 -> 411 | E21: =E18+E20 -> 465 | F21: =F18+F20 -> 293 | G21: =G18+G20 -> 367 | I21: =I18+I20 -> 10 | J21: =J18+J20 -> 50 | K21: =K18+K20 -> 0 | L21: =L18+L20 -> 0 | M21: =M18+M20 -> 10 | O21: =O18+O20 -> 494 | P21: =P18+P20 -> 461 | Q21: =Q18+Q20 -> 465 | R21: =R18+R20 -> 293 | S21: =S18+S20 -> 377
B23: Interest income | C23: 10 | D23: 10 | E23: 10 | F23: 10 | G23: 10 | O23: =C23+I23 -> 10 | P23: =D23+J23 -> 10 | Q23: =E23+K23 -> 10 | R23: =F23+L23 -> 10 | S23: =G23+M23 -> 10
B24: Interest expenses | C24: -5 | D24: -5 | E24: -5 | F24: -5 | G24: -5 | O24: =C24+I24 -> -5 | P24: =D24+J24 -> -5 | Q24: =E24+K24 -> -5 | R24: =F24+L24 -> -5 | S24: =G24+M24 -> -5
B25: Profit before tax | C25: =C21+C23+C24 -> 489 | D25: =D21+D23+D24 -> 416 | E25: =E21+E23+E24 -> 470 | F25: =F21+F23+F24 -> 298 | G25: =G21+G23+G24 -> 372 | I25: =I21+I23+I24 -> 10 | J25: =J21+J23+J24 -> 50 | K25: =K21+K23+K24 -> 0 | L25: =L21+L23+L24 -> 0 | M25: =M21+M23+M24 -> 10 | O25: =O21+O23+O24 -> 499 | P25: =P21+P23+P24 -> 466 | Q25: =Q21+Q23+Q24 -> 470 | R25: =R21+R23+R24 -> 298 | S25: =S21+S23+S24 -> 382
B27: Income tax | C27: -50 | D27: -50 | E27: -50 | F27: -50 | G27: -50 | O27: =C27+I27 -> -50 | P27: =D27+J27 -> -50 | Q27: =E27+K27 -> -50 | R27: =F27+L27 -> -50 | S27: =G27+M27 -> -50
B28: Net result | C28: =C25+C27 -> 439 | D28: =D25+D27 -> 366 | E28: =E25+E27 -> 420 | F28: =F25+F27 -> 248 | G28: =G25+G27 -> 322 | I28: =I25+I27 -> 10 | J28: =J25+J27 -> 50 | K28: =K25+K27 -> 0 | L28: =L25+L27 -> 0 | M28: =M25+M27 -> 10 | O28: =O25+O27 -> 449 | P28: =P25+P27 -> 416 | Q28: =Q25+Q27 -> 420 | R28: =R25+R27 -> 248 | S28: =S25+S27 -> 332
B33: Key metrics
B34: Year-on-year growth in revenues | D34: =D6/C6-1 -> -0.12135177 | E34: =E6/D6-1 -> 0.075174825 | F34: =F6/E6-1 -> -0.23739837 | G34: =G6/F6-1 -> 0.15138593
B35: Net result as % of total revenues | C35: =C28/C$8 -> 0.67434716 | D35: =D28/D$8 -> 0.63986014 | E35: =E28/E$8 -> 0.68292683 | F35: =F28/F$8 -> 0.52878465 | G35: =G28/G$8 -> 0.5962963
B36: Average number of FTEs | C36: 10 | D36: 10 | E36: 10 | F36: 10 | G36: 10
B37: Salaries per FTE | C37: =-C13/C36 -> 2.3 | D37: =-D13/D36 -> 2.3 | E37: =-E13/E36 -> 2.3 | F37: =-F13/F36 -> 2.3 | G37: =-G13/G36 -> 2.3

Sheet Revenue breakdown
B2: Revenue breakdown
B4: Revenue by product line | P4: Revenue by product line (values) | AB4: Revenue by product line as % of total (2023)
B5: Currency: [Insert currency unit e.g, EUR M or USD millions) | C5: 2019 | D5: =C5+1 -> 2020 | E5: =D5+1 -> 2021 | F5: =E5+1 -> 2022 | G5: =F5+1 -> 2023 | I5: As % of total revenue | J5: 2019 | K5: =J5+1 -> 2020 | L5: =K5+1 -> 2021 | M5: =L5+1 -> 2022 | N5: =M5+1 -> 2023
B7: Product 1 | C7: 9 | D7: 24 | E7: 69 | F7: 25 | G7: 34 | I7: Product 1 | J7: =C7/C$17 -> 0.013824885 | K7: =D7/D$17 -> 0.041958042 | L7: =E7/E$17 -> 0.11219512 | M7: =F7/F$17 -> 0.053304904 | N7: =G7/G$17 -> 0.062962963
B8: Product 2 | C8: 43 | D8: 86 | E8: 55 | F8: 48 | G8: 80 | I8: Product 2 | J8: =C8/C$17 -> 0.066052227 | K8: =D8/D$17 -> 0.15034965 | L8: =E8/E$17 -> 0.089430894 | M8: =F8/F$17 -> 0.10234542 | N8: =G8/G$17 -> 0.14814815
B9: Product 3 | C9: 44 | D9: 18 | E9: 59 | F9: 44 | G9: 80 | I9: Product 3 | J9: =C9/C$17 -> 0.067588326 | K9: =D9/D$17 -> 0.031468531 | L9: =E9/E$17 -> 0.095934959 | M9: =F9/F$17 -> 0.093816631 | N9: =G9/G$17 -> 0.14814815
B10: Product 4 | C10: 94 | D10: 73 | E10: 33 | F10: 59 | G10: 68 | I10: Product 4 | J10: =C10/C$17 -> 0.14439324 | K10: =D10/D$17 -> 0.12762238 | L10: =E10/E$17 -> 0.053658537 | M10: =F10/F$17 -> 0.12579957 | N10: =G10/G$17 -> 0.12592593
B11: Product 5 | C11: 82 | D11: 50 | E11: 60 | F11: 45 | G11: 4 | I11: Product 5 | J11: =C11/C$17 -> 0.12596006 | K11: =D11/D$17 -> 0.087412587 | L11: =E11/E$17 -> 0.097560976 | M11: =F11/F$17 -> 0.095948827 | N11: =G11/G$17 -> 0.0074074074
B12: Product 6 | C12: 92 | D12: 49 | E12: 78 | F12: 19 | G12: 99 | I12: Product 6 | J12: =C12/C$17 -> 0.14132104 | K12: =D12/D$17 -> 0.085664336 | L12: =E12/E$17 -> 0.12682927 | M12: =F12/F$17 -> 0.040511727 | N12: =G12/G$17 -> 0.18333333
B13: Product 7 | C13: 95 | D13: 56 | E13: 58 | F13: 79 | G13: 47 | I13: Product 7 | J13: =C13/C$17 -> 0.14592934 | K13: =D13/D$17 -> 0.097902098 | L13: =E13/E$17 -> 0.094308943 | M13: =F13/F$17 -> 0.1684435 | N13: =G13/G$17 -> 0.087037037
B14: Product 8 | C14: 99 | D14: 66 | E14: 76 | F14: 49 | G14: 59 | I14: Product 8 | J14: =C14/C$17 -> 0.15207373 | K14: =D14/D$17 -> 0.11538462 | L14: =E14/E$17 -> 0.12357724 | M14: =F14/F$17 -> 0.10447761 | N14: =G14/G$17 -> 0.10925926
B15: Product 9 | C15: 34 | D15: 66 | E15: 46 | F15: 3 | G15: 42 | I15: Product 9 | J15: =C15/C$17 -> 0.052227343 | K15: =D15/D$17 -> 0.11538462 | L15: =E15/E$17 -> 0.074796748 | M15: =F15/F$17 -> 0.0063965885 | N15: =G15/G$17 -> 0.077777778
B16: Product 10 | C16: 59 | D16: 84 | E16: 81 | F16: 98 | G16: 27 | I16: Product 10 | J16: =C16/C$17 -> 0.0906298 | K16: =D16/D$17 -> 0.14685315 | L16: =E16/E$17 -> 0.13170732 | M16: =F16/F$17 -> 0.20895522 | N16: =G16/G$17 -> 0.05
B17: Total revenues | C17: =SUM(C7:C16) -> 651 | D17: =SUM(D7:D16) -> 572 | E17: =SUM(E7:E16) -> 615 | F17: =SUM(F7:F16) -> 469 | G17: =SUM(G7:G16) -> 540 | I17: Total | J17: =SUM(J7:J16) -> 1 | K17: =SUM(K7:K16) -> 1 | L17: =SUM(L7:L16) -> 1 | M17: =SUM(M7:M16) -> 1 | N17: =SUM(N7:N16) -> 1
B18: Year-on-year growth | D18: =D17/C17-1 -> -0.12135177 | E18: =E17/D17-1 -> 0.075174825 | F18: =F17/E17-1 -> -0.23739837 | G18: =G17/F17-1 -> 0.15138593
B24: Revenue by country | P24: Revenue by country | AB24: Revenue by country as % of total (2023)
B25: Currency: [Insert currency unit e.g, EUR M or USD millions) | C25: 2019 | D25: =C25+1 -> 2020 | E25: =D25+1 -> 2021 | F25: =E25+1 -> 2022 | G25: =F25+1 -> 2023 | I25: As % of total revenue | J25: 2019 | K25: =J25+1 -> 2020 | L25: =K25+1 -> 2021 | M25: =L25+1 -> 2022 | N25: =M25+1 -> 2023
B27: Country 1 | C27: 190 | D27: 201 | E27: 216 | F27: 176 | G27: 262 | I27: Country 1 | J27: =C27/C$32 -> 0.29185868 | K27: =D27/D$32 -> 0.3513986 | L27: =E27/E$32 -> 0.35121951 | M27: =F27/F$32 -> 0.37526652 | N27: =G27/G$32 -> 0.48518519
B28: Country 2 | C28: 93 | D28: 150 | E28: 127 | F28: 101 | G28: 69 | I28: Country 2 | J28: =C28/C$32 -> 0.14285714 | K28: =D28/D$32 -> 0.26223776 | L28: =E28/E$32 -> 0.20650407 | M28: =F28/F$32 -> 0.21535181 | N28: =G28/G$32 -> 0.12777778
B29: Country 3 | C29: 18 | D29: 18 | E29: 18 | F29: 18 | G29: 18 | I29: Country 3 | J29: =C29/C$32 -> 0.02764977 | K29: =D29/D$32 -> 0.031468531 | L29: =E29/E$32 -> 0.029268293 | M29: =F29/F$32 -> 0.038379531 | N29: =G29/G$32 -> 0.033333333
B30: Country 4 | C30: 10 | D30: 10 | E30: 10 | F30: 10 | G30: 10 | I30: Country 4 | J30: =C30/C$32 -> 0.015360983 | K30: =D30/D$32 -> 0.017482517 | L30: =E30/E$32 -> 0.016260163 | M30: =F30/F$32 -> 0.021321962 | N30: =G30/G$32 -> 0.018518519
B31: Country 5 | C31: 340 | D31: 193 | E31: 244 | F31: 164 | G31: 181 | I31: Country 5 | J31: =C31/C$32 -> 0.52227343 | K31: =D31/D$32 -> 0.33741259 | L31: =E31/E$32 -> 0.39674797 | M31: =F31/F$32 -> 0.34968017 | N31: =G31/G$32 -> 0.33518519
B32: Total revenues | C32: =SUM(C27:C31) -> 651 | D32: =SUM(D27:D31) -> 572 | E32: =SUM(E27:E31) -> 615 | F32: =SUM(F27:F31) -> 469 | G32: =SUM(G27:G31) -> 540 | I32: Total | J32: =SUM(J27:J31) -> 1 | K32: =SUM(K27:K31) -> 1 | L32: =SUM(L27:L31) -> 1 | M32: =SUM(M27:M31) -> 1 | N32: =SUM(N27:N31) -> 1
B33: Year-on-year growth | D33: =D32/C32-1 -> -0.12135177 | E33: =E32/D32-1 -> 0.075174825 | F33: =F32/E32-1 -> -0.23739837 | G33: =G32/F32-1 -> 0.15138593
B45: Revenue by channel
B46: Currency: [Insert currency unit e.g, EUR M or USD millions) | C46: 2019 | D46: =C46+1 -> 2020 | E46: =D46+1 -> 2021 | F46: =E46+1 -> 2022 | G46: =F46+1 -> 2023 | I46: As % of total revenue | J46: 2019 | K46: =J46+1 -> 2020 | L46: =K46+1 -> 2021 | M46: =L46+1 -> 2022 | N46: =M46+1 -> 2023 | P46: Revenue by channel as % of total (2023)
B48: Store | C48: 230 | D48: 230 | E48: 230 | F48: 230 | G48: 230 | I48: Store | J48: =C48/C$32 -> 0.35330261 | K48: =D48/D$32 -> 0.4020979 | L48: =E48/E$32 -> 0.37398374 | M48: =F48/F$32 -> 0.49040512 | N48: =G48/G$32 -> 0.42592593
B49: Online | C49: 180 | D49: 180 | E49: 180 | F49: 180 | G49: 180 | I49: Online | J49: =C49/C$32 -> 0.2764977 | K49: =D49/D$32 -> 0.31468531 | L49: =E49/E$32 -> 0.29268293 | M49: =F49/F$32 -> 0.38379531 | N49: =G49/G$32 -> 0.33333333
B50: Distributors | C50: 241 | D50: 162 | E50: 205 | F50: 59 | G50: 130 | I50: Distributors | J50: =C50/C$32 -> 0.37019969 | K50: =D50/D$32 -> 0.28321678 | L50: =E50/E$32 -> 0.33333333 | M50: =F50/F$32 -> 0.12579957 | N50: =G50/G$32 -> 0.24074074
B51: Total revenues | C51: =SUM(C48:C50) -> 651 | D51: =SUM(D48:D50) -> 572 | E51: =SUM(E48:E50) -> 615 | F51: =SUM(F48:F50) -> 469 | G51: =SUM(G48:G50) -> 540 | I51: Total | J51: =SUM(J48:J50) -> 1 | K51: =SUM(K48:K50) -> 1 | L51: =SUM(L48:L50) -> 1 | M51: =SUM(M48:M50) -> 1 | N51: =SUM(N48:N50) -> 1
B52: Year-on-year growth | D52: =D51/C51-1 -> -0.12135177 | E52: =E51/D51-1 -> 0.075174825 | F52: =F51/E51-1 -> -0.23739837 | G52: =G51/F51-1 -> 0.15138593

Sheet Cost of good sold breakdown
B2: Cost of goods sold breakdown
B4: Currency: [Insert currency unit e.g, EUR M or USD millions) | C4: 2019 | D4: =C4+1 -> 2020 | E4: =D4+1 -> 2021 | F4: =E4+1 -> 2022 | G4: =F4+1 -> 2023 | I4: As % of total COGS | J4: 2019 | K4: =J4+1 -> 2020 | L4: =K4+1 -> 2021 | M4: =L4+1 -> 2022 | N4: =M4+1 -> 2023
B6: Raw materials | C6: 7 | D6: 10 | E6: 2 | F6: 12 | G6: 7 | I6: Raw materials | J6: =C6/C$13 -> 0.1147541 | K6: =D6/D$13 -> 0.18181818 | L6: =E6/E$13 -> 0.045454545 | M6: =F6/F$13 -> 0.17142857 | N6: =G6/G$13 -> 0.10447761
B7: Direct materials | C7: 13 | D7: 6 | E7: 9 | F7: 20 | G7: 2 | I7: Direct materials | J7: =C7/C$13 -> 0.21311475 | K7: =D7/D$13 -> 0.10909091 | L7: =E7/E$13 -> 0.20454545 | M7: =F7/F$13 -> 0.28571429 | N7: =G7/G$13 -> 0.029850746
B8: Indirect materials | C8: 3 | D8: 9 | E8: 2 | F8: 9 | G8: 9 | I8: Indirect materials | J8: =C8/C$13 -> 0.049180328 | K8: =D8/D$13 -> 0.16363636 | L8: =E8/E$13 -> 0.045454545 | M8: =F8/F$13 -> 0.12857143 | N8: =G8/G$13 -> 0.13432836
B9: Manufacturing overhead | C9: 14 | D9: 3 | E9: 1 | F9: 10 | G9: 18 | I9: Manufacturing overhead | J9: =C9/C$13 -> 0.2295082 | K9: =D9/D$13 -> 0.054545455 | L9: =E9/E$13 -> 0.022727273 | M9: =F9/F$13 -> 0.14285714 | N9: =G9/G$13 -> 0.26865672
B10: Price difference | C10: 6 | D10: 10 | E10: 6 | F10: 3 | G10: 15 | I10: Price difference | J10: =C10/C$13 -> 0.098360656 | K10: =D10/D$13 -> 0.18181818 | L10: =E10/E$13 -> 0.13636364 | M10: =F10/F$13 -> 0.042857143 | N10: =G10/G$13 -> 0.2238806
B11: Freight | C11: 11 | D11: 12 | E11: 13 | F11: 14 | G11: 15 | I11: Freight | J11: =C11/C$13 -> 0.18032787 | K11: =D11/D$13 -> 0.21818182 | L11: =E11/E$13 -> 0.29545455 | M11: =F11/F$13 -> 0.2 | N11: =G11/G$13 -> 0.2238806
B12: Other costs | C12: 7 | D12: 5 | E12: 11 | F12: 2 | G12: 1 | I12: Other costs | J12: =C12/C$13 -> 0.1147541 | K12: =D12/D$13 -> 0.090909091 | L12: =E12/E$13 -> 0.25 | M12: =F12/F$13 -> 0.028571429 | N12: =G12/G$13 -> 0.014925373
B13: Total cost of goods sold | C13: =SUM(C6:C12) -> 61 | D13: =SUM(D6:D12) -> 55 | E13: =SUM(E6:E12) -> 44 | F13: =SUM(F6:F12) -> 70 | G13: =SUM(G6:G12) -> 67 | I13: Total | J13: =SUM(J6:J12) -> 1 | K13: =SUM(K6:K12) -> 1 | L13: =SUM(L6:L12) -> 1 | M13: =SUM(M6:M12) -> 1 | N13: =SUM(N6:N12) -> 1

Sheet Operating expenses breakdown
B2: Operating expenses breakdown
B4: Currency: [Insert currency unit e.g, EUR M or USD millions) | C4: 2019 | D4: =C4+1 -> 2020 | E4: =D4+1 -> 2021 | F4: =E4+1 -> 2022 | G4: =F4+1 -> 2023 | I4: As % of total operating expenses | J4: 2019 | K4: =J4+1 -> 2020 | L4: =K4+1 -> 2021 | M4: =L4+1 -> 2022 | N4: =M4+1 -> 2023
B6: Gross salaries | C6: 7 | D6: 10 | E6: 2 | F6: 12 | G6: 7 | I6: Gross salaries | J6: =C6/C$28 -> 0.072916667 | K6: =D6/D$28 -> 0.11111111 | L6: =E6/E$28 -> 0.02739726 | M6: =F6/F$28 -> 0.11111111 | N6: =G6/G$28 -> 0.08045977
B7: Social charges e.g., pension plans | C7: 13 | D7: 6 | E7: 9 | F7: 20 | G7: 2 | I7: Social charges e.g., pension plans | J7: =C7/C$28 -> 0.13541667 | K7: =D7/D$28 -> 0.066666667 | L7: =E7/E$28 -> 0.12328767 | M7: =F7/F$28 -> 0.18518519 | N7: =G7/G$28 -> 0.022988506
B8: Bonuses | C8: 3 | D8: 9 | E8: 2 | F8: 9 | G8: 9 | I8: Bonuses | J8: =C8/C$28 -> 0.03125 | K8: =D8/D$28 -> 0.1 | L8: =E8/E$28 -> 0.02739726 | M8: =F8/F$28 -> 0.083333333 | N8: =G8/G$28 -> 0.10344828
B9: Total salaries | C9: =SUM(C6:C8) -> 23 | D9: =SUM(D6:D8) -> 25 | E9: =SUM(E6:E8) -> 13 | F9: =SUM(F6:F8) -> 41 | G9: =SUM(G6:G8) -> 18 | I9: Total salaries | J9: =C9/C$28 -> 0.23958333 | K9: =D9/D$28 -> 0.27777778 | L9: =E9/E$28 -> 0.17808219 | M9: =F9/F$28 -> 0.37962963 | N9: =G9/G$28 -> 0.20689655
B11: Rent | C11: 6 | D11: 10 | E11: 6 | F11: 3 | G11: 15 | I11: Rent | J11: =C11/C$28 -> 0.0625 | K11: =D11/D$28 -> 0.11111111 | L11: =E11/E$28 -> 0.082191781 | M11: =F11/F$28 -> 0.027777778 | N11: =G11/G$28 -> 0.17241379
B12: Office supplies | C12: 3 | D12: 5 | E12: 5 | F12: 5 | G12: 1 | I12: Office supplies | J12: =C12/C$28 -> 0.03125 | K12: =D12/D$28 -> 0.055555556 | L12: =E12/E$28 -> 0.068493151 | M12: =F12/F$28 -> 0.046296296 | N12: =G12/G$28 -> 0.011494253
B13: Maintenance | C13: 11 | D13: 12 | E13: 13 | F13: 14 | G13: 15 | I13: Maintenance | J13: =C13/C$28 -> 0.11458333 | K13: =D13/D$28 -> 0.13333333 | L13: =E13/E$28 -> 0.17808219 | M13: =F13/F$28 -> 0.12962963 | N13: =G13/G$28 -> 0.17241379
B14: Total housing | C14: =SUM(C11:C13) -> 20 | D14: =SUM(D11:D13) -> 27 | E14: =SUM(E11:E13) -> 24 | F14: =SUM(F11:F13) -> 22 | G14: =SUM(G11:G13) -> 31 | I14: Total housing | J14: =C14/C$28 -> 0.20833333 | K14: =D14/D$28 -> 0.3 | L14: =E14/E$28 -> 0.32876712 | M14: =F14/F$28 -> 0.2037037 | N14: =G14/G$28 -> 0.35632184
B16: Marketing | C16: 10 | D16: 3 | E16: 3 | F16: 7 | G16: 6 | I16: Marketing | J16: =C16/C$28 -> 0.10416667 | K16: =D16/D$28 -> 0.033333333 | L16: =E16/E$28 -> 0.04109589 | M16: =F16/F$28 -> 0.064814815 | N16: =G16/G$28 -> 0.068965517
B17: Sales materials | C17: 10 | D17: 3 | E17: 6 | F17: 5 | G17: 1 | I17: Sales materials | J17: =C17/C$28 -> 0.10416667 | K17: =D17/D$28 -> 0.033333333 | L17: =E17/E$28 -> 0.082191781 | M17: =F17/F$28 -> 0.046296296 | N17: =G17/G$28 -> 0.011494253
B18: Website | C18: 10 | D18: 6 | E18: 1 | F18: 9 | G18: 9 | I18: Website | J18: =C18/C$28 -> 0.10416667 | K18: =D18/D$28 -> 0.066666667 | L18: =E18/E$28 -> 0.01369863 | M18: =F18/F$28 -> 0.083333333 | N18: =G18/G$28 -> 0.10344828
B19: Other sales costs | C19: 1 | D19: 9 | E19: 4 | F19: 9 | G19: 3 | I19: Other sales costs | J19: =C19/C$28 -> 0.010416667 | K19: =D19/D$28 -> 0.1 | L19: =E19/E$28 -> 0.054794521 | M19: =F19/F$28 -> 0.083333333 | N19: =G19/G$28 -> 0.034482759
B20: Total selling expenses | C20: =SUM(C16:C19) -> 31 | D20: =SUM(D16:D19) -> 21 | E20: =SUM(E16:E19) -> 14 | F20: =SUM(F16:F19) -> 30 | G20: =SUM(G16:G19) -> 19 | I20: Total selling expenses | J20: =C20/C$28 -> 0.32291667 | K20: =D20/D$28 -> 0.23333333 | L20: =E20/E$28 -> 0.19178082 | M20: =F20/F$28 -> 0.27777778 | N20: =G20/G$28 -> 0.2183908
B22: Insurance | C22: 7 | D22: 5 | E22: 1 | F22: 2 | G22: 1 | I22: Insurance | J22: =C22/C$28 -> 0.072916667 | K22: =D22/D$28 -> 0.055555556 | L22: =E22/E$28 -> 0.01369863 | M22: =F22/F$28 -> 0.018518519 | N22: =G22/G$28 -> 0.011494253
B23: Accounting | C23: 5 | D23: 1 | E23: 3 | F23: 1 | G23: 7 | I23: Accounting | J23: =C23/C$28 -> 0.052083333 | K23: =D23/D$28 -> 0.011111111 | L23: =E23/E$28 -> 0.04109589 | M23: =F23/F$28 -> 0.0092592593 | N23: =G23/G$28 -> 0.08045977
B24: Other administrative expenses | C24: 3 | D24: 6 | E24: 7 | F24: 10 | G24: 10 | I24: Other administrative expenses | J24: =C24/C$28 -> 0.03125 | K24: =D24/D$28 -> 0.066666667 | L24: =E24/E$28 -> 0.095890411 | M24: =F24/F$28 -> 0.092592593 | N24: =G24/G$28 -> 0.11494253
B25: Total administrative expenses | C25: =SUM(C22:C24) -> 15 | D25: =SUM(D22:D24) -> 12 | E25: =SUM(E22:E24) -> 11 | F25: =SUM(F22:F24) -> 13 | G25: =SUM(G22:G24) -> 18 | I25: Total administrative expenses | J25: =C25/C$28 -> 0.15625 | K25: =D25/D$28 -> 0.13333333 | L25: =E25/E$28 -> 0.15068493 | M25: =F25/F$28 -> 0.12037037 | N25: =G25/G$28 -> 0.20689655
B27: Other operating expenses | C27: 7 | D27: 5 | E27: 11 | F27: 2 | G27: 1 | I27: Other operating expenses | J27: =C27/C$28 -> 0.072916667 | K27: =D27/D$28 -> 0.055555556 | L27: =E27/E$28 -> 0.15068493 | M27: =F27/F$28 -> 0.018518519 | N27: =G27/G$28 -> 0.011494253
B28: Total cost of goods sold | C28: =C9+C14+C20+C25+C27 -> 96 | D28: =D9+D14+D20+D25+D27 -> 90 | E28: =E9+E14+E20+E25+E27 -> 73 | F28: =F9+F14+F20+F25+F27 -> 108 | G28: =G9+G14+G20+G25+G27 -> 87 | I28: Total | J28: =SUM(J6:J8,J11:J13,J16:J19,J22:J24,J27) -> 1 | K28: =SUM(K6:K8,K11:K13,K16:K19,K22:K24,K27) -> 1 | L28: =SUM(L6:L8,L11:L13,L16:L19,L22:L24,L27) -> 1 | M28: =SUM(M6:M8,M11:M13,M16:M19,M22:M24,M27) -> 1 | N28: =SUM(N6:N8,N11:N13,N16:N19,N22:N24,N27) -> 1
