Workbook

Sheet Slideworks guide
B2: How to use this Excel model:
B3: Use this Excel to more explicitly spell out your project costs and expected income streams, as well as calculate the investment case and perform sensitivity analyses. Can be used as an extended version of the preliminary business case from the file "1. Slideworks_business_case_BACK OF ENVELOPE_template.xlsx"
B5: Five ways to calculate when a project is a good business case:
B6: Method | C6: Answers the question… | D6: Expressed in… | E6: Typically used for…
B7: Breakeven analysis | C7: How many sales are needed to recoup the investment? | D7: Units sold | E7: Market-focused projects like product development and new market expansion
B8: Return on investment (ROI) | C8: How much profit can we earn? | D8: Percentage | E8: Projects with significant upfront costs, like facilities projects, and productivity projects that accumulate benefits over time
B9: Payback period | C9: How long will it take to recoup the investment? | D9: Months or years | E9: Projects with significant upfront costs, like facilities projects, and productivity projects that accumulate benefits over time
B10: Net present value (NPV) | C10: How much is this project worth to the business? | D10: Dollars/Euro etc. | E10: Projects with large expenditures
B11: Internal rate of return (IRR) | C11: What rate of return will this project deliver over its lifecycle? | D11: Percentage | E11: Projects that a company expects to extend indefinitely, especially those requiring borrowing.
B13: Formatting:
B15: Light yellow cells are input fields
B16: All other cells are calculated

Sheet Project overview
B2: Project description
B4: Insert a brief description of the project
B15: Project details
B17: Project name: | C17: [Insert name of project]
B18: Project category: | C18: [Insert category, if relevant]
B19: Business unit/team: | C19: [Insert business unit/team, if relevant]
B20: Model version: | C20: 1
B21: Date: | C21: [Insert date]
B22: Model prepared by: | C22: [Insert name and title]
B23: Project leader: | C23: [Insert name and title]
B24: Project sponsor: | C24: [Insert name and title]

Sheet Project financials
B2: Project financials
B4: Project financials | C4: Entry | D4: Year 1 | E4: Year 2 | F4: Year 3 | G4: Year 4 | H4: Year 5 | J4: Total
B6: Costs
B7: Project investments | C7: ='Project costs'!C18 -> 1055000 | D7: ='Project costs'!D18 -> 106000 | E7: ='Project costs'!E18 -> 71000 | F7: ='Project costs'!F18 -> 54000 | G7: ='Project costs'!G18 -> 43000 | H7: ='Project costs'!H18 -> 26000 | J7: =SUM(C7:H7) -> 1355000
B8: Ongoing project costs | C8: ='Project costs'!C41 -> 0 | D8: ='Project costs'!D41 -> 35000 | E8: ='Project costs'!E41 -> 35000 | F8: ='Project costs'!F41 -> 35000 | G8: ='Project costs'!G41 -> 35000 | H8: ='Project costs'!H41 -> 35000 | J8: =SUM(C8:H8) -> 175000
B10: Benefits
B11: Revenue creation | C11: ='Project benefits'!C15 -> 0 | D11: ='Project benefits'!D15 -> 450000 | E11: ='Project benefits'!E15 -> 630000 | F11: ='Project benefits'!F15 -> 630000 | G11: ='Project benefits'!G15 -> 630000 | H11: ='Project benefits'!H15 -> 540000 | J11: =SUM(C11:H11) -> 2880000
B12: Cost savings | C12: ='Project benefits'!C27 -> 0 | D12: ='Project benefits'!D27 -> 60000 | E12: ='Project benefits'!E27 -> 80000 | F12: ='Project benefits'!F27 -> 40000 | G12: ='Project benefits'!G27 -> 0 | H12: ='Project benefits'!H27 -> 0 | J12: =SUM(C12:H12) -> 180000
B14: Preliminary cash flow | C14: =C12+C11-C8-C7 -> -1055000 | D14: =D12+D11-D8-D7 -> 369000 | E14: =E12+E11-E8-E7 -> 604000 | F14: =F12+F11-F8-F7 -> 581000 | G14: =G12+G11-G8-G7 -> 552000 | H14: =H12+H11-H8-H7 -> 479000 | J14: =J12+J11-J8-J7 -> 1530000
B16: Cumulative cash flow | C16: =C14 -> -1055000 | D16: =C16+D14 -> -686000 | E16: =D16+E14 -> -82000 | F16: =E16+F14 -> 499000 | G16: =F16+G14 -> 1051000 | H16: =G16+H14 -> 1530000 | J16: =H16 -> 1530000
B20: Investment case
B22: Discount rate | C22: 0.05
B23: Net present value (NPV): | C23: =NPV(C22,D14:H14)+C14 -> 1175604.8
B25: Internal rate of return: | C25: =IRR(C14:H14) -> 0.37923873
B27: Payback period | C27: =ROUND(COUNTIF(14:14,"<0")+(-D16/E14),2) & " years" -> 2.14 years | D27: Note: To calculate fractional year find last year where cumulative cash flow is zero (row 16). Then divide that number by the cash flow (row 14) of the following year. In this example these cells are D16 and E14.
B29: Return on investment (ROI): | C29: =(J11+J12-J8-J7)/(J8+J7) -> 1
B31: Break-even analysis:
B32: Gross profit per [unit/sale] | C32: 3000
B33: Net project costs (annual incremental costs + initial/one-off investments) | C33: =J7+D8 -> 1390000
B35: Break-even point: | C35: =ROUNDUP(C33/C32,0) & " units sold" -> 464 units sold
B70: Sensitivity analysis
B72: Note: Use whatever metric makes sense to test sensitivity to e.g., market size, cost overrun etc. and adjust rest of columns to match that
B73: Growth in customer base | C73: Share of increased customer base that results in new customers | D73: Sales volume | E73: Revenue per sale | F73: Revenue | G73: Increase in revenue
B74: 0 | C74: 0.7 | D74: 10000 | E74: 45 | F74: =+D74*E74 -> 450000 | G74: -
B75: =+B74+0.1 -> 0.1 | C75: =C74 -> 0.7 | D75: =D$74*(1+B75*C75) -> 10700 | E75: =E74 -> 45 | F75: =+D75*E75 -> 481500 | G75: =F75/F$74-1 -> 0.07
B76: =+B75+0.1 -> 0.2 | C76: =C75 -> 0.7 | D76: =D$74*(1+B76*C76) -> 11400 | E76: =E75 -> 45 | F76: =+D76*E76 -> 513000 | G76: =F76/F$74-1 -> 0.14
B77: =+B76+0.1 -> 0.3 | C77: =C76 -> 0.7 | D77: =D$74*(1+B77*C77) -> 12100 | E77: =E76 -> 45 | F77: =+D77*E77 -> 544500 | G77: =F77/F$74-1 -> 0.21
B78: =+B77+0.1 -> 0.4 | C78: =C77 -> 0.7 | D78: =D$74*(1+B78*C78) -> 12800 | E78: =E77 -> 45 | F78: =+D78*E78 -> 576000 | G78: =F78/F$74-1 -> 0.28
B79: =+B78+0.1 -> 0.5 | C79: =C78 -> 0.7 | D79: =D$74*(1+B79*C79) -> 13500 | E79: =E78 -> 45 | F79: =+D79*E79 -> 607500 | G79: =F79/F$74-1 -> 0.35
B80: =+B79+0.1 -> 0.6 | C80: =C79 -> 0.7 | D80: =D$74*(1+B80*C80) -> 14200 | E80: =E79 -> 45 | F80: =+D80*E80 -> 639000 | G80: =F80/F$74-1 -> 0.42
B81: =+B80+0.1 -> 0.7 | C81: =C80 -> 0.7 | D81: =D$74*(1+B81*C81) -> 14900 | E81: =E80 -> 45 | F81: =+D81*E81 -> 670500 | G81: =F81/F$74-1 -> 0.49
B82: =+B81+0.1 -> 0.8 | C82: =C81 -> 0.7 | D82: =D$74*(1+B82*C82) -> 15600 | E82: =E81 -> 45 | F82: =+D82*E82 -> 702000 | G82: =F82/F$74-1 -> 0.56
B83: =+B82+0.1 -> 0.9 | C83: =C82 -> 0.7 | D83: =D$74*(1+B83*C83) -> 16300 | E83: =E82 -> 45 | F83: =+D83*E83 -> 733500 | G83: =F83/F$74-1 -> 0.63
B84: =+B83+0.1 -> 1 | C84: =C83 -> 0.7 | D84: =D$74*(1+B84*C84) -> 17000 | E84: =E83 -> 45 | F84: =+D84*E84 -> 765000 | G84: =F84/F$74-1 -> 0.7

Sheet Project costs
B2: Project costs
B4: Project investments | C4: Entry | D4: Year 1 | E4: Year 2 | F4: Year 3 | G4: Year 4 | H4: Year 5 | J4: Total | L4: Comment/rationale
B6: Capital expenditures
B7: Investment category #1 (e.g., production equipment) | C7: 0 | D7: 55000 | E7: 55000 | F7: 40000 | G7: 30000 | H7: 20000 | J7: =SUM(C7:H7) -> 200000 | L7: [Insert comment]
B8: Investment category #2 (e.g., IT hardware) | C8: 0 | D8: 20000 | E8: 6000 | F8: 6000 | G8: 6000 | H8: 2000 | J8: =SUM(C8:H8) -> 40000 | L8: [Insert comment]
B9: Investment category #3 | C9: 0 | D9: 31000 | E9: 10000 | F9: 8000 | G9: 7000 | H9: 4000 | J9: =SUM(C9:H9) -> 60000 | L9: [Insert comment]
B10: Investment category #4 | C10: 0 | D10: 0 | E10: 0 | F10: 0 | G10: 0 | H10: 0 | J10: =SUM(C10:H10) -> 0 | L10: [Insert comment]
B11: Investment category #5 | C11: 0 | D11: 0 | E11: 0 | F11: 0 | G11: 0 | H11: 0 | J11: =SUM(C11:H11) -> 0 | L11: [Insert comment]
B13: Project expenses (one-time expenses)
B14: Expense #1 (e.g., prototype development) | C14: 80000 | D14: 0 | E14: 0 | F14: 0 | G14: 0 | H14: 0 | J14: =SUM(C14:H14) -> 80000 | L14: [Insert comment]
B15: Expense #2 | C15: 800000 | D15: 0 | E15: 0 | F15: 0 | G15: 0 | H15: 0 | J15: =SUM(C15:H15) -> 800000 | L15: [Insert comment]
B16: Expense #3 | C16: 175000 | D16: 0 | E16: 0 | F16: 0 | G16: 0 | H16: 0 | J16: =SUM(C16:H16) -> 175000 | L16: [Insert comment]
B18: Total project investments (Capex) | C18: =SUM(C5:C17) -> 1055000 | D18: =SUM(D5:D17) -> 106000 | E18: =SUM(E5:E17) -> 71000 | F18: =SUM(F5:F17) -> 54000 | G18: =SUM(G5:G17) -> 43000 | H18: =SUM(H5:H17) -> 26000 | J18: =SUM(C18:H18) -> 1355000
B22: Ongoing project costs | C22: Year 0 | D22: Year 1 | E22: Year 2 | F22: Year 3 | G22: Year 4 | H22: Year 5 | J22: Total | L22: Comment/rationale
B24: Operating expenses | D24: 25000 | E24: 25000 | F24: 25000 | G24: 25000 | H24: 25000 | J24: =SUM(C24:H24) -> 125000 | L24: [Insert comment]
B25: Ongoing cost #1 (e.g., salaries) | D25: 5000 | E25: 5000 | F25: 5000 | G25: 5000 | H25: 5000 | J25: =SUM(C25:H25) -> 25000 | L25: [Insert comment]
B26: Ongoing cost #2 (e.g., personnel expenses) | D26: 5000 | E26: 5000 | F26: 5000 | G26: 5000 | H26: 5000 | J26: =SUM(C26:H26) -> 25000 | L26: [Insert comment]
B27: Ongoing cost #3 (e.g., software licenses) | D27: 0 | E27: 0 | F27: 0 | G27: 0 | H27: 0 | J27: =SUM(C27:H27) -> 0 | L27: [Insert comment]
B28: Ongoing cost #4 | D28: 0 | E28: 0 | F28: 0 | G28: 0 | H28: 0 | J28: =SUM(C28:H28) -> 0 | L28: [Insert comment]
B29: Ongoing cost #5 | D29: 0 | E29: 0 | F29: 0 | G29: 0 | H29: 0 | J29: =SUM(C29:H29) -> 0 | L29: [Insert comment]
B31: Marketing and sales expenses
B32: Ongoing cost #6 (e.g., Meta) | D32: 0 | E32: 0 | F32: 0 | G32: 0 | H32: 0 | J32: =SUM(C32:H32) -> 0 | L32: [Insert comment]
B33: Ongoing cost #7 | D33: 0 | E33: 0 | F33: 0 | G33: 0 | H33: 0 | J33: =SUM(C33:H33) -> 0 | L33: [Insert comment]
B34: Ongoing cost #8 | D34: 0 | E34: 0 | F34: 0 | G34: 0 | H34: 0 | J34: =SUM(C34:H34) -> 0 | L34: [Insert comment]
B35: Ongoing cost #9 | D35: 0 | E35: 0 | F35: 0 | G35: 0 | H35: 0 | J35: =SUM(C35:H35) -> 0 | L35: [Insert comment]
B36: Ongoing cost #10 | D36: 0 | E36: 0 | F36: 0 | G36: 0 | H36: 0 | J36: =SUM(C36:H36) -> 0 | L36: [Insert comment]
D37: 0 | E37: 0 | F37: 0 | G37: 0 | H37: 0 | J37: =SUM(C37:H37) -> 0 | L37: [Insert comment]
B38: Other expenses
B39: Ongoing cost #11 | D39: 0 | E39: 0 | F39: 0 | G39: 0 | H39: 0 | J39: =SUM(C39:H39) -> 0 | L39: [Insert comment]
B41: Total ongoing project costs | D41: =SUM(D23:D40) -> 35000 | E41: =SUM(E23:E40) -> 35000 | F41: =SUM(F23:F40) -> 35000 | G41: =SUM(G23:G40) -> 35000 | H41: =SUM(H23:H40) -> 35000 | J41: =SUM(C41:H41) -> 175000

Sheet Project benefits
B2: Project benefits
B4: Revenue creation | C4: Entry | D4: Year 1 | E4: Year 2 | F4: Year 3 | G4: Year 4 | H4: Year 5 | J4: Total
B6: Revenues
B7: Revenue stream #1 (e.g., new customer subscriptions) | C7: 0 | D7: 750000 | E7: 1050000 | F7: 1050000 | G7: 1050000 | H7: 900000 | J7: =SUM(C7:H7) -> 4800000
B8: Revenue stream #2 (e.g., ad sales) | C8: 0 | D8: 0 | E8: 0 | F8: 0 | G8: 0 | H8: 0 | J8: =SUM(C8:H8) -> 0
B9: Revenue stream #3 | C9: 0 | D9: 0 | E9: 0 | F9: 0 | G9: 0 | H9: 0 | J9: =SUM(C9:H9) -> 0
B11: Cost of goods sold
B12: Cost of goods sold (COGS), (% of revenue) | C12: 0.4 | D12: =C12 -> 0.4 | E12: =D12 -> 0.4 | F12: =E12 -> 0.4 | G12: =F12 -> 0.4 | H12: =G12 -> 0.4
B13: Cost of goods sold (COGS) | C13: =C12*SUM(C7:C9) -> 0 | D13: =D12*SUM(D7:D9) -> 300000 | E13: =E12*SUM(E7:E9) -> 420000 | F13: =F12*SUM(F7:F9) -> 420000 | G13: =G12*SUM(G7:G9) -> 420000 | H13: =H12*SUM(H7:H9) -> 360000 | J13: =SUM(C13:H13) -> 1920000
B15: Gross margin from new revenue streams | C15: =SUM(C7:C9)-C13 -> 0 | D15: =SUM(D7:D9)-D13 -> 450000 | E15: =SUM(E7:E9)-E13 -> 630000 | F15: =SUM(F7:F9)-F13 -> 630000 | G15: =SUM(G7:G9)-G13 -> 630000 | H15: =SUM(H7:H9)-H13 -> 540000 | J15: =SUM(C15:H15) -> 2880000
B19: Cost savings | C19: Entry | D19: Year 1 | E19: Year 2 | F19: Year 3 | G19: Year 4 | H19: Year 5 | J19: Total
B21: Cost savings #1 (e.g., less manual processing) | C21: 0 | D21: 60000 | E21: 80000 | F21: 40000 | G21: 0 | H21: 0 | J21: =SUM(C21:H21) -> 180000
B22: Cost savings #2 | C22: 0 | D22: 0 | E22: 0 | F22: 0 | G22: 0 | H22: 0 | J22: =SUM(C22:H22) -> 0
B23: Cost savings #3 | C23: 0 | D23: 0 | E23: 0 | F23: 0 | G23: 0 | H23: 0 | J23: =SUM(C23:H23) -> 0
B24: Cost savings #4 | C24: 0 | D24: 0 | E24: 0 | F24: 0 | G24: 0 | H24: 0 | J24: =SUM(C24:H24) -> 0
B25: Cost savings #5 | C25: 0 | D25: 0 | E25: 0 | F25: 0 | G25: 0 | H25: 0 | J25: =SUM(C25:H25) -> 0
B27: Total cost savings | C27: =SUM(C20:C26) -> 0 | D27: =SUM(D20:D26) -> 60000 | E27: =SUM(E20:E26) -> 80000 | F27: =SUM(F20:F26) -> 40000 | G27: =SUM(G20:G26) -> 0 | H27: =SUM(H20:H26) -> 0 | J27: =SUM(C27:H27) -> 180000
