Workbook

Sheet Slideworks guide
B2: How to use this Excel model:
B3: Use this Excel to compare different solution options. Adjust assumptions under each option and compare return on investment calculations.
B5: Five ways to calculate when a project is a good business case:
B6: Method | C6: Answers the question… | D6: Expressed in… | E6: Typically used for…
B7: Breakeven analysis | C7: How many sales are needed to recoup the investment? | D7: Units sold | E7: Market-focused projects like product development and new market expansion
B8: Return on investment (ROI) | C8: How much profit can we earn? | D8: Percentage | E8: Projects with significant upfront costs, like facilities projects, and productivity projects that accumulate benefits over time
B9: Payback period | C9: How long will it take to recoup the investment? | D9: Months or years | E9: Projects with significant upfront costs, like facilities projects, and productivity projects that accumulate benefits over time
B10: Net present value (NPV) | C10: How much is this project worth to the business? | D10: Dollars/Euro etc. | E10: Projects with large expenditures
B11: Internal rate of return (IRR) | C11: What rate of return will this project deliver over its lifecycle? | D11: Percentage | E11: Projects that a company expects to extend indefinitely, especially those requiring borrowing.
B13: Formatting:
B15: Light yellow cells are input fields
B16: All other cells are calculated

Sheet Project overview
B2: Project description
B4: Insert a brief description of the project
B15: Project details
B17: Project name: | C17: [Insert name of project]
B18: Project category: | C18: [Insert category, if relevant]
B19: Business unit/team: | C19: [Insert business unit/team, if relevant]
B20: Model version: | C20: 1
B21: Date: | C21: [Insert date]
B22: Model prepared by: | C22: [Insert name and title]
B23: Project leader: | C23: [Insert name and title]
B24: Project sponsor: | C24: [Insert name and title]

Sheet Options comparison
B2: Business case options comparison
B3: Overview of investment case for each option
C5: Investment | D5: Net present value (NPV) | E5: Internal rate of return (IRR) | F5: Discounted payback period (years) | G5: Return on investment (ROI) | H5: Description
B6: ='Option 1'!C$4 -> [Insert name of option e.g., Do minimum] | C6: =-SUM('Option 1'!C$101:H$101) -> 162000 | D6: ='Option 1'!C$148 -> 1218882 | E6: ='Option 1'!C$150 -> 0.63730727 | F6: ='Option 1'!C$152 -> 4.32 years | G6: ='Option 1'!C$154 -> 6.5239628 | H6: ='Option 1'!C$5 -> [Insert brief description of scenario]
B7: ='Option 2'!C$4 -> [Insert name of option e.g., Focus on new revenue] | C7: =-SUM('Option 2'!C$101:H$101) -> 162000 | D7: ='Option 2'!C$148 -> 1131482.8 | E7: ='Option 2'!C$150 -> 0.59458994 | F7: ='Option 2'!C$152 -> 5.99 years | G7: ='Option 2'!C$154 -> 5.9844616 | H7: ='Option 1'!C$5 -> [Insert brief description of scenario]
B8: ='Option 3'!C$4 -> [Insert name of option e.g., High growth] | C8: =-SUM('Option 3'!C$101:H$101) -> 306000 | D8: ='Option 3'!C$148 -> 1573574.1 | E8: ='Option 3'!C$150 -> 0.50706001 | F8: ='Option 3'!C$152 -> 5.93 years | G8: ='Option 3'!C$154 -> 4.1423992 | H8: ='Option 1'!C$5 -> [Insert brief description of scenario]
B23: Revenue and cost savings | C23: ='Option 1'!C37 -> Entry | D23: ='Option 1'!D37 -> Year 1 | E23: ='Option 1'!E37 -> Year 2 | F23: ='Option 1'!F37 -> Year 3 | G23: ='Option 1'!G37 -> Year 4 | H23: ='Option 1'!H37 -> Year 5 | I23: ='Option 1'!I37 -> Exit
B24: =B6 -> [Insert name of option e.g., Do minimum] | C24: ='Option 1'!C$44+'Option 1'!C$49 -> 0 | D24: ='Option 1'!D$44+'Option 1'!D$49 -> 145000 | E24: ='Option 1'!E$44+'Option 1'!E$49 -> 134000 | F24: ='Option 1'!F$44+'Option 1'!F$49 -> 152000 | G24: ='Option 1'!G$44+'Option 1'!G$49 -> 188000 | H24: ='Option 1'!H$44+'Option 1'!H$49 -> 230000
B25: =B7 -> [Insert name of option e.g., Focus on new revenue] | C25: ='Option 2'!C$44+'Option 2'!C$49 -> 0 | D25: ='Option 2'!D$44+'Option 2'!D$49 -> 95000 | E25: ='Option 2'!E$44+'Option 2'!E$49 -> 104000 | F25: ='Option 2'!F$44+'Option 2'!F$49 -> 122000 | G25: ='Option 2'!G$44+'Option 2'!G$49 -> 158000 | H25: ='Option 2'!H$44+'Option 2'!H$49 -> 200000
B26: =B8 -> [Insert name of option e.g., High growth] | C26: ='Option 3'!C$44+'Option 3'!C$49 -> 0 | D26: ='Option 3'!D$44+'Option 3'!D$49 -> 265000 | E26: ='Option 3'!E$44+'Option 3'!E$49 -> 254000 | F26: ='Option 3'!F$44+'Option 3'!F$49 -> 290000 | G26: ='Option 3'!G$44+'Option 3'!G$49 -> 368000 | H26: ='Option 3'!H$44+'Option 3'!H$49 -> 410000
B28: EBITDA | C28: =C23 -> Entry | D28: =D23 -> Year 1 | E28: =E23 -> Year 2 | F28: =F23 -> Year 3 | G28: =G23 -> Year 4 | H28: =H23 -> Year 5 | I28: =I23 -> Exit
B29: =B6 -> [Insert name of option e.g., Do minimum] | C29: ='Option 1'!C$72 -> 0 | D29: ='Option 1'!D$72 -> 95000 | E29: ='Option 1'!E$72 -> 84000 | F29: ='Option 1'!F$72 -> 102000 | G29: ='Option 1'!G$72 -> 138000 | H29: ='Option 1'!H$72 -> 180000
B30: =B7 -> [Insert name of option e.g., Focus on new revenue] | C30: ='Option 2'!C$72 -> 0 | D30: ='Option 2'!D$72 -> 69000 | E30: ='Option 2'!E$72 -> 78000 | F30: ='Option 2'!F$72 -> 96000 | G30: ='Option 2'!G$72 -> 132000 | H30: ='Option 2'!H$72 -> 174000
B31: =B8 -> [Insert name of option e.g., High growth] | C31: ='Option 3'!C$72 -> 0 | D31: ='Option 3'!D$72 -> 125000 | E31: ='Option 3'!E$72 -> 114000 | F31: ='Option 3'!F$72 -> 150000 | G31: ='Option 3'!G$72 -> 228000 | H31: ='Option 3'!H$72 -> 270000
B33: Total cash flows | C33: =C23 -> Entry | D33: =D23 -> Year 1 | E33: =E23 -> Year 2 | F33: =F23 -> Year 3 | G33: =G23 -> Year 4 | H33: =H23 -> Year 5 | I33: =I23 -> Exit
B34: =B6 -> [Insert name of option e.g., Do minimum] | C34: ='Option 1'!C$115 -> -162000 | D34: ='Option 1'!D$115 -> 25477.315 | E34: ='Option 1'!E$115 -> 24788.663 | F34: ='Option 1'!F$115 -> 39604.966 | G34: ='Option 1'!G$115 -> 67063.208 | H34: ='Option 1'!H$115 -> 101137.17 | I34: ='Option 1'!I$115 -> 2123880.5
B35: =B7 -> [Insert name of option e.g., Focus on new revenue] | C35: ='Option 2'!C$115 -> -162000 | D35: ='Option 2'!D$115 -> 5197.3151 | E35: ='Option 2'!E$115 -> 20108.663 | F35: ='Option 2'!F$115 -> 34924.966 | G35: ='Option 2'!G$115 -> 62383.208 | H35: ='Option 2'!H$115 -> 96457.168 | I35: ='Option 2'!I$115 -> 2025600.5
B36: =B8 -> [Insert name of option e.g., High growth] | C36: ='Option 3'!C$115 -> -306000 | D36: ='Option 3'!D$115 -> -7055.1781 | E36: ='Option 3'!E$115 -> 13254.263 | F36: ='Option 3'!F$115 -> 41211.572 | G36: ='Option 3'!G$115 -> 99605.907 | H36: ='Option 3'!H$115 -> 142369.29 | I36: ='Option 3'!I$115 -> 2989755.1

Sheet Option 1
B2: Option 1: | C2: [Insert name of option e.g., Do minimum]
B4: Option 1: | C4: =C2 -> [Insert name of option e.g., Do minimum]
B5: Description: | C5: [Insert brief description of scenario]
B7: Assumptions | C7: Entry | D7: Year 1 | E7: Year 2 | F7: Year 3 | G7: Year 4 | H7: Year 5 | I7: Exit
B9: Business Case Timing
B10: Start Date | C10: 45778
B11: Fiscal Year Date | C11: 45838
B12: Date | C12: =C10 -> 45778 | D12: =DATE(YEAR($C$11)+D13,6,30) -> 46203 | E12: =DATE(YEAR($C$11)+E13,6,30) -> 46568 | F12: =DATE(YEAR($C$11)+F13,6,30) -> 46934 | G12: =DATE(YEAR($C$11)+G13,6,30) -> 47299 | H12: =DATE(YEAR($C$11)+H13,6,30) -> 47664 | I12: =DATE(YEAR($C$11)+I13,6,30) -> 48029
B13: Time periods | C13: 0 | D13: 1 | E13: =D13+1 -> 2 | F13: =E13+1 -> 3 | G13: =F13+1 -> 4 | H13: =G13+1 -> 5 | I13: =H13+1 -> 6
B14: Year fraction | D14: =YEARFRAC(C12,D12) -> 1.1638889 | E14: =YEARFRAC(D12,E12) -> 1 | F14: =YEARFRAC(E12,F12) -> 1 | G14: =YEARFRAC(F12,G12) -> 1 | H14: =YEARFRAC(G12,H12) -> 1
B16: Operations
B17: Cost of goods sold (% of revenue) | C17: 0.4
B18: Tax rate | C18: 0.22
B19: Depreciation & amortization | C19: 0.1
B21: Project investment
B22: Buffer on capex investments | C22: 0.2
B24: Working capital
B25: Accounts receivable (days) | C25: 30
B26: Inventory (days) | C26: 60
B27: Accounts payable (days) | C27: 30
B29: Financing
B30: Interest rate on debt (%) | C30: 0.1
B31: Yearly debt repayments (% of total debt) | C31: 0.2
B33: DCF Analysis
B34: Discount Rate | C34: 0.1
B35: Perpetual Growth Rate | C35: 0.05
B37: Business case | C37: Entry | D37: Year 1 | E37: Year 2 | F37: Year 3 | G37: Year 4 | H37: Year 5 | I37: Exit
B39: Operations
B41: Revenues
B42: New revenue generated | D42: 75000 | E42: 90000 | F42: 120000 | G42: 180000 | H42: 250000
B43: Cost of goods sold (COGS) | D43: =D42*$C$17 -> 30000 | E43: =E42*$C$17 -> 36000 | F43: =F42*$C$17 -> 48000 | G43: =G42*$C$17 -> 72000 | H43: =H42*$C$17 -> 100000
B44: Gross margin | C44: =(C42-C43) -> 0 | D44: =(D42-D43) -> 45000 | E44: =(E42-E43) -> 54000 | F44: =(F42-F43) -> 72000 | G44: =(G42-G43) -> 108000 | H44: =(H42-H43) -> 150000
B46: Cost savings
B47: Cost savings #1 | D47: 100000 | E47: 80000 | F47: 80000 | G47: 80000 | H47: 80000
B48: Cost savings #1 | D48: 0 | E48: 0 | F48: 0 | G48: 0 | H48: 0
B49: Total cost savings | C49: =SUM(C47:C48) -> 0 | D49: =SUM(D47:D48) -> 100000 | E49: =SUM(E47:E48) -> 80000 | F49: =SUM(F47:F48) -> 80000 | G49: =SUM(G47:G48) -> 80000 | H49: =SUM(H47:H48) -> 80000
B51: Ongoing project costs
B53: Operating expenses
B54: Ongoing cost #1 (e.g., salaries) | D54: 30000 | E54: =D54 -> 30000 | F54: =E54 -> 30000 | G54: =F54 -> 30000 | H54: =G54 -> 30000
B55: Ongoing cost #2 (e.g., personnel expenses) | D55: 15000 | E55: =D55 -> 15000 | F55: =E55 -> 15000 | G55: =F55 -> 15000 | H55: =G55 -> 15000
B56: Ongoing cost #3 (e.g., software licenses) | D56: 4000 | E56: =D56 -> 4000 | F56: =E56 -> 4000 | G56: =F56 -> 4000 | H56: =G56 -> 4000
B57: Ongoing cost #4 | D57: 0 | E57: 0 | F57: 0 | G57: 0 | H57: 0
B58: Ongoing cost #5 | D58: 0 | E58: 0 | F58: 0 | G58: 0 | H58: 0
B60: Marketing and sales expenses
B61: Ongoing cost #6 (e.g., Meta) | D61: 1000 | E61: 1000 | F61: 1000 | G61: 1000 | H61: 1000
B62: Ongoing cost #7 | D62: 0 | E62: 0 | F62: 0 | G62: 0 | H62: 0
B63: Ongoing cost #8 | D63: 0 | E63: 0 | F63: 0 | G63: 0 | H63: 0
B64: Ongoing cost #9 | D64: 0 | E64: 0 | F64: 0 | G64: 0 | H64: 0
B65: Ongoing cost #10 | D65: 0 | E65: 0 | F65: 0 | G65: 0 | H65: 0
B67: Other expenses
B68: Ongoing cost #11 | D68: 0 | E68: 0 | F68: 0 | G68: 0 | H68: 0
B70: Total ongoing project costs | C70: =-SUM(C52:C69) -> 0 | D70: =-SUM(D52:D69) -> -50000 | E70: =-SUM(E52:E69) -> -50000 | F70: =-SUM(F52:F69) -> -50000 | G70: =-SUM(G52:G69) -> -50000 | H70: =-SUM(H52:H69) -> -50000
B72: Earnings before interest, tax, depreciation, amortization (EBITDA) | C72: =C44+C49+C70 -> 0 | D72: =D44+D49+D70 -> 95000 | E72: =E44+E49+E70 -> 84000 | F72: =F44+F49+F70 -> 102000 | G72: =G44+G49+G70 -> 138000 | H72: =H44+H49+H70 -> 180000
B74: Depreciation | C74: =C162 -> 0 | D74: =D162 -> 16200 | E74: =E162 -> 14580 | F74: =F162 -> 13122 | G74: =G162 -> 11809.8 | H74: =H162 -> 10628.82
B75: Interest | C75: =C171 -> 0 | D75: =D171 -> 16200 | E75: =E171 -> 12960 | F75: =F171 -> 9720 | G75: =G171 -> 6480 | H75: =H171 -> 3240
B76: Earnings before tax | C76: =C72-C74-C75 -> 0 | D76: =D72-D74-D75 -> 62600 | E76: =E72-E74-E75 -> 56460 | F76: =F72-F74-F75 -> 79158 | G76: =G72-G74-G75 -> 119710.2 | H76: =H72-H74-H75 -> 166131.18
B78: Tax | C78: =C76*$C$18 -> 0 | D78: =D76*$C$18 -> 13772 | E78: =E76*$C$18 -> 12421.2 | F78: =F76*$C$18 -> 17414.76 | G78: =G76*$C$18 -> 26336.244 | H78: =H76*$C$18 -> 36548.86
B79: Earnings after tax | C79: =C76-C78 -> 0 | D79: =D76-D78 -> 48828 | E79: =E76-E78 -> 44038.8 | F79: =F76-F78 -> 61743.24 | G79: =G76-G78 -> 93373.956 | H79: =H76-H78 -> 129582.32
B81: Plus: Depreciation and amortization | C81: =C74 -> 0 | D81: =D74 -> 16200 | E81: =E74 -> 14580 | F81: =F74 -> 13122 | G81: =G74 -> 11809.8 | H81: =H74 -> 10628.82
B82: Less: Changes in working capital | C82: =C178 -> 0 | D82: =D178 -> 7150.6849 | E82: =E178 -> 1430.137 | F82: =F178 -> 2860.274 | G82: =G178 -> 5720.5479 | H82: =H178 -> 6673.9726
B83: Cash flow from operations | C83: =C79+C81-C82 -> 0 | D83: =D79+D81-D82 -> 57877.315 | E83: =E79+E81-E82 -> 57188.663 | F83: =F79+F81-F82 -> 72004.966 | G83: =G79+G81-G82 -> 99463.208 | H83: =H79+H81-H82 -> 133537.17
B85: Investments
B87: Capital expenditures
B88: Investment category #1 (e.g., production equipment) | C88: 80000 | D88: 0 | E88: 0 | F88: 0 | G88: 0 | H88: 0
B89: Investment category #2 (e.g., IT hardware) | C89: 25000 | D89: 0 | E89: 0 | F89: 0 | G89: 0 | H89: 0
B90: Investment category #3 | C90: 20000 | D90: 0 | E90: 0 | F90: 0 | G90: 0 | H90: 0
B91: Investment category #4 | C91: 0 | D91: 0 | E91: 0 | F91: 0 | G91: 0 | H91: 0
B92: Investment category #5 | C92: 0 | D92: 0 | E92: 0 | F92: 0 | G92: 0 | H92: 0
B94: Project expenses (one-time expenses)
B95: Expense #1 (e.g., prototype development) | C95: 10000 | D95: 0 | E95: 0 | F95: 0 | G95: 0 | H95: 0
B96: Expense #2 | C96: 0 | D96: 0 | E96: 0 | F96: 0 | G96: 0 | H96: 0
B97: Expense #3 | C97: 0 | D97: 0 | E97: 0 | F97: 0 | G97: 0 | H97: 0
B99: Buffer | C99: =$C$22*SUM(C88:C97) -> 27000 | D99: =$C$22*SUM(D88:D97) -> 0 | E99: =$C$22*SUM(E88:E97) -> 0 | F99: =$C$22*SUM(F88:F97) -> 0 | G99: =$C$22*SUM(G88:G97) -> 0 | H99: =$C$22*SUM(H88:H97) -> 0
B101: Cash flow from investments (Capex) | C101: =-SUM(C87:C100) -> -162000 | D101: =-SUM(D87:D100) -> 0 | E101: =-SUM(E87:E100) -> 0 | F101: =-SUM(F87:F100) -> 0 | G101: =-SUM(G87:G100) -> 0 | H101: =-SUM(H87:H100) -> 0
B103: Financing
B105: Financing costs
B106: Debt repayment | C106: =C168 -> 0 | D106: =D168 -> 32400 | E106: =E168 -> 32400 | F106: =F168 -> 32400 | G106: =G168 -> 32400 | H106: =H168 -> 32400
B108: Cash flow from financing | C108: =-SUM(C106:C106) -> 0 | D108: =-SUM(D106:D106) -> -32400 | E108: =-SUM(E106:E106) -> -32400 | F108: =-SUM(F106:F106) -> -32400 | G108: =-SUM(G106:G106) -> -32400 | H108: =-SUM(H106:H106) -> -32400
B110: Total cash flow
B112: Cash flow from operations | C112: =C83 -> 0 | D112: =D83 -> 57877.315 | E112: =E83 -> 57188.663 | F112: =F83 -> 72004.966 | G112: =G83 -> 99463.208 | H112: =H83 -> 133537.17
B113: Cash flow from investments | C113: =C101 -> -162000 | D113: =D101 -> 0 | E113: =E101 -> 0 | F113: =F101 -> 0 | G113: =G101 -> 0 | H113: =H101 -> 0
B114: Cash flow from financing | C114: =C108 -> 0 | D114: =D108 -> -32400 | E114: =E108 -> -32400 | F114: =F108 -> -32400 | G114: =G108 -> -32400 | H114: =H108 -> -32400 | I114: Terminal value
B115: Total cash flow | C115: =C112+C113+C114 -> -162000 | D115: =D112+D113+D114 -> 25477.315 | E115: =E112+E113+E114 -> 24788.663 | F115: =F112+F113+F114 -> 39604.966 | G115: =G112+G113+G114 -> 67063.208 | H115: =H112+H113+H114 -> 101137.17 | I115: =H115*(1+C35)/(C34-C35) -> 2123880.5
B117: Cumulative cash flow | C117: =C115 -> -162000 | D117: =C117+D115 -> -136522.68 | E117: =D117+E115 -> -111734.02 | F117: =E117+F115 -> -72129.056 | G117: =F117+G115 -> -5065.8478 | H117: =G117+H115 -> 96071.32 | I117: =I115+H117 -> 2219951.8
B141: Discounted cash flow (DCF) | C141: Entry | D141: Year 1 | E141: Year 2 | F141: Year 3 | G141: Year 4 | H141: Year 5 | I141: Exit
B143: Period | C143: =C13 -> 0 | D143: =D13 -> 1 | E143: =E13 -> 2 | F143: =F13 -> 3 | G143: =G13 -> 4 | H143: =H13 -> 5 | I143: =I13 -> 6
B144: Total cash flow | C144: =C115 -> -162000 | D144: =D115 -> 25477.315 | E144: =E115 -> 24788.663 | F144: =F115 -> 39604.966 | G144: =G115 -> 67063.208 | H144: =H115 -> 101137.17 | I144: =I115 -> 2123880.5
B145: Present value of total cash flow | C145: =C144/((1+$C$34)^C143) -> -162000 | D145: =D144/((1+$C$34)^D143) -> 23161.196 | E145: =E144/((1+$C$34)^E143) -> 20486.498 | F145: =F144/((1+$C$34)^F143) -> 29755.797 | G145: =G144/((1+$C$34)^G143) -> 45805.073 | H145: =H144/((1+$C$34)^H143) -> 62798.224 | I145: =I144/((1+$C$34)^I143) -> 1198875.2
B146: Cumulative present value of total cash flow | C146: =C145 -> -162000 | D146: =C146+D145 -> -138838.8 | E146: =D146+E145 -> -118352.31 | F146: =E146+F145 -> -88596.509 | G146: =F146+G145 -> -42791.435 | H146: =G146+H145 -> 20006.789 | I146: =H146+I145 -> 1218882
B148: Net present value (NPV): | C148: =NPV(C34,D144:I144)+C144 -> 1218882
B150: Internal rate of return: | C150: =IRR(C144:I144) -> 0.63730727
B152: Payback period | C152: {=ROUND(IFERROR(COUNTIF(D146:I146,"<"&0)+INDEX(D152:I152,,COUNTIF(D146:I146,"<"&0)+1),"> Nil"),2) &" years"} -> 4.32 years | D152: =IF(D146<0," - ",D146/D145) -> - | E152: =IF(E146<0," - ",E146/E145) -> - | F152: =IF(F146<0," - ",F146/F145) -> - | G152: =IF(G146<0," - ",G146/G145) -> - | H152: =IF(H146<0," - ",H146/H145) -> 0.31858844 | I152: =IF(I146<0," - ",I146/I145) -> 1.016688
B154: Return on investment (ROI): | C154: =ABS(C148/SUM(C101:H101))-1 -> 6.5239628
B157: Supporting calculations | C157: Entry | D157: Year 1 | E157: Year 2 | F157: Year 3 | G157: Year 4 | H157: Year 5 | I157: Exit
B159: Depreciation schedule
B160: Property, plant & equipment (PPE) opening | C160: 0 | D160: =C163 -> 162000 | E160: =D163 -> 145800 | F160: =E163 -> 131220 | G160: =F163 -> 118098 | H160: =G163 -> 106288.2 | I160: =H163 -> 95659.38
B161: Plus capex/project investments | C161: =-C101 -> 162000 | D161: =-D101 -> 0 | E161: =-E101 -> 0 | F161: =-F101 -> 0 | G161: =-G101 -> 0 | H161: =-H101 -> 0
B162: Less depreciation | C162: 0 | D162: =D160*$C$19 -> 16200 | E162: =E160*$C$19 -> 14580 | F162: =F160*$C$19 -> 13122 | G162: =G160*$C$19 -> 11809.8 | H162: =H160*$C$19 -> 10628.82
B163: Property, plant & equipment (PPE) closing | C163: =C160+C161-C162 -> 162000 | D163: =D160+D161-D162 -> 145800 | E163: =E160+E161-E162 -> 131220 | F163: =F160+F161-F162 -> 118098 | G163: =G160+G161-G162 -> 106288.2 | H163: =H160+H161-H162 -> 95659.38
B165: Debt & interest schedule
...

Sheet Option 2
B2: Option 2: | C2: [Insert name of option e.g., Focus on new revenue]
B4: Option 2: | C4: =C2 -> [Insert name of option e.g., Focus on new revenue]
B5: Description: | C5: [Insert brief description of scenario]
B7: Assumptions | C7: Entry | D7: Year 1 | E7: Year 2 | F7: Year 3 | G7: Year 4 | H7: Year 5 | I7: Exit
B9: Business Case Timing
B10: Start Date | C10: 45778
B11: Fiscal Year Date | C11: 45838
B12: Date | C12: =C10 -> 45778 | D12: =DATE(YEAR($C$11)+D13,6,30) -> 46203 | E12: =DATE(YEAR($C$11)+E13,6,30) -> 46568 | F12: =DATE(YEAR($C$11)+F13,6,30) -> 46934 | G12: =DATE(YEAR($C$11)+G13,6,30) -> 47299 | H12: =DATE(YEAR($C$11)+H13,6,30) -> 47664 | I12: =DATE(YEAR($C$11)+I13,6,30) -> 48029
B13: Time periods | C13: 0 | D13: 1 | E13: =D13+1 -> 2 | F13: =E13+1 -> 3 | G13: =F13+1 -> 4 | H13: =G13+1 -> 5 | I13: =H13+1 -> 6
B14: Year fraction | D14: =YEARFRAC(C12,D12) -> 1.1638889 | E14: =YEARFRAC(D12,E12) -> 1 | F14: =YEARFRAC(E12,F12) -> 1 | G14: =YEARFRAC(F12,G12) -> 1 | H14: =YEARFRAC(G12,H12) -> 1
B16: Operations
B17: Cost of goods sold (% of revenue) | C17: 0.4
B18: Tax rate | C18: 0.22
B19: Depreciation & amortization | C19: 0.1
B21: Project investment
B22: Buffer on capex investments | C22: 0.2
B24: Working capital
B25: Accounts receivable (days) | C25: 30
B26: Inventory (days) | C26: 60
B27: Accounts payable (days) | C27: 30
B29: Financing
B30: Interest rate on debt (%) | C30: 0.1
B31: Yearly debt repayments (% of total debt) | C31: 0.2
B33: DCF Analysis
B34: Discount Rate | C34: 0.1
B35: Perpetual Growth Rate | C35: 0.05
B37: Business case | C37: Entry | D37: Year 1 | E37: Year 2 | F37: Year 3 | G37: Year 4 | H37: Year 5 | I37: Exit
B39: Operations
B41: Revenues
B42: New revenue generated | D42: 75000 | E42: 90000 | F42: 120000 | G42: 180000 | H42: 250000
B43: Cost of goods sold (COGS) | D43: =D42*$C$17 -> 30000 | E43: =E42*$C$17 -> 36000 | F43: =F42*$C$17 -> 48000 | G43: =G42*$C$17 -> 72000 | H43: =H42*$C$17 -> 100000
B44: Gross margin | C44: =(C42-C43) -> 0 | D44: =(D42-D43) -> 45000 | E44: =(E42-E43) -> 54000 | F44: =(F42-F43) -> 72000 | G44: =(G42-G43) -> 108000 | H44: =(H42-H43) -> 150000
B46: Cost savings
B47: Cost savings #1 | D47: 50000 | E47: 50000 | F47: 50000 | G47: 50000 | H47: 50000
B48: Cost savings #1 | D48: 0 | E48: 0 | F48: 0 | G48: 0 | H48: 0
B49: Total cost savings | C49: =SUM(C47:C48) -> 0 | D49: =SUM(D47:D48) -> 50000 | E49: =SUM(E47:E48) -> 50000 | F49: =SUM(F47:F48) -> 50000 | G49: =SUM(G47:G48) -> 50000 | H49: =SUM(H47:H48) -> 50000
B51: Ongoing project costs
B53: Operating expenses
B54: Ongoing cost #1 (e.g., salaries) | D54: 20000 | E54: =D54 -> 20000 | F54: =E54 -> 20000 | G54: =F54 -> 20000 | H54: =G54 -> 20000
B55: Ongoing cost #2 (e.g., personnel expenses) | D55: 5000 | E55: =D55 -> 5000 | F55: =E55 -> 5000 | G55: =F55 -> 5000 | H55: =G55 -> 5000
B56: Ongoing cost #3 (e.g., software licenses) | D56: 0 | E56: =D56 -> 0 | F56: =E56 -> 0 | G56: =F56 -> 0 | H56: =G56 -> 0
B57: Ongoing cost #4 | D57: 0 | E57: 0 | F57: 0 | G57: 0 | H57: 0
B58: Ongoing cost #5 | D58: 0 | E58: 0 | F58: 0 | G58: 0 | H58: 0
B60: Marketing and sales expenses
B61: Ongoing cost #6 (e.g., Meta) | D61: 1000 | E61: 1000 | F61: 1000 | G61: 1000 | H61: 1000
B62: Ongoing cost #7 | D62: 0 | E62: 0 | F62: 0 | G62: 0 | H62: 0
B63: Ongoing cost #8 | D63: 0 | E63: 0 | F63: 0 | G63: 0 | H63: 0
B64: Ongoing cost #9 | D64: 0 | E64: 0 | F64: 0 | G64: 0 | H64: 0
B65: Ongoing cost #10 | D65: 0 | E65: 0 | F65: 0 | G65: 0 | H65: 0
B67: Other expenses
B68: Ongoing cost #11 | D68: 0 | E68: 0 | F68: 0 | G68: 0 | H68: 0
B70: Total ongoing project costs | C70: =-SUM(C52:C69) -> 0 | D70: =-SUM(D52:D69) -> -26000 | E70: =-SUM(E52:E69) -> -26000 | F70: =-SUM(F52:F69) -> -26000 | G70: =-SUM(G52:G69) -> -26000 | H70: =-SUM(H52:H69) -> -26000
B72: Earnings before interest, tax, depreciation, amortization (EBITDA) | C72: =C44+C49+C70 -> 0 | D72: =D44+D49+D70 -> 69000 | E72: =E44+E49+E70 -> 78000 | F72: =F44+F49+F70 -> 96000 | G72: =G44+G49+G70 -> 132000 | H72: =H44+H49+H70 -> 174000
B74: Depreciation | C74: =C162 -> 0 | D74: =D162 -> 16200 | E74: =E162 -> 14580 | F74: =F162 -> 13122 | G74: =G162 -> 11809.8 | H74: =H162 -> 10628.82
B75: Interest | C75: =C171 -> 0 | D75: =D171 -> 16200 | E75: =E171 -> 12960 | F75: =F171 -> 9720 | G75: =G171 -> 6480 | H75: =H171 -> 3240
B76: Earnings before tax | C76: =C72-C74-C75 -> 0 | D76: =D72-D74-D75 -> 36600 | E76: =E72-E74-E75 -> 50460 | F76: =F72-F74-F75 -> 73158 | G76: =G72-G74-G75 -> 113710.2 | H76: =H72-H74-H75 -> 160131.18
B78: Tax | C78: =C76*$C$18 -> 0 | D78: =D76*$C$18 -> 8052 | E78: =E76*$C$18 -> 11101.2 | F78: =F76*$C$18 -> 16094.76 | G78: =G76*$C$18 -> 25016.244 | H78: =H76*$C$18 -> 35228.86
B79: Earnings after tax | C79: =C76-C78 -> 0 | D79: =D76-D78 -> 28548 | E79: =E76-E78 -> 39358.8 | F79: =F76-F78 -> 57063.24 | G79: =G76-G78 -> 88693.956 | H79: =H76-H78 -> 124902.32
B81: Plus: Depreciation and amortization | C81: =C74 -> 0 | D81: =D74 -> 16200 | E81: =E74 -> 14580 | F81: =F74 -> 13122 | G81: =G74 -> 11809.8 | H81: =H74 -> 10628.82
B82: Less: Changes in working capital | C82: =C178 -> 0 | D82: =D178 -> 7150.6849 | E82: =E178 -> 1430.137 | F82: =F178 -> 2860.274 | G82: =G178 -> 5720.5479 | H82: =H178 -> 6673.9726
B83: Cash flow from operations | C83: =C79+C81-C82 -> 0 | D83: =D79+D81-D82 -> 37597.315 | E83: =E79+E81-E82 -> 52508.663 | F83: =F79+F81-F82 -> 67324.966 | G83: =G79+G81-G82 -> 94783.208 | H83: =H79+H81-H82 -> 128857.17
B85: Investments
B87: Capital expenditures
B88: Investment category #1 (e.g., production equipment) | C88: 80000 | D88: 0 | E88: 0 | F88: 0 | G88: 0 | H88: 0
B89: Investment category #2 (e.g., IT hardware) | C89: 25000 | D89: 0 | E89: 0 | F89: 0 | G89: 0 | H89: 0
B90: Investment category #3 | C90: 20000 | D90: 0 | E90: 0 | F90: 0 | G90: 0 | H90: 0
B91: Investment category #4 | C91: 0 | D91: 0 | E91: 0 | F91: 0 | G91: 0 | H91: 0
B92: Investment category #5 | C92: 0 | D92: 0 | E92: 0 | F92: 0 | G92: 0 | H92: 0
B94: Project expenses (one-time expenses)
B95: Expense #1 (e.g., prototype development) | C95: 10000 | D95: 0 | E95: 0 | F95: 0 | G95: 0 | H95: 0
B96: Expense #2 | C96: 0 | D96: 0 | E96: 0 | F96: 0 | G96: 0 | H96: 0
B97: Expense #3 | C97: 0 | D97: 0 | E97: 0 | F97: 0 | G97: 0 | H97: 0
B99: Buffer | C99: =$C$22*SUM(C88:C97) -> 27000 | D99: =$C$22*SUM(D88:D97) -> 0 | E99: =$C$22*SUM(E88:E97) -> 0 | F99: =$C$22*SUM(F88:F97) -> 0 | G99: =$C$22*SUM(G88:G97) -> 0 | H99: =$C$22*SUM(H88:H97) -> 0
B101: Cash flow from investments (Capex) | C101: =-SUM(C87:C100) -> -162000 | D101: =-SUM(D87:D100) -> 0 | E101: =-SUM(E87:E100) -> 0 | F101: =-SUM(F87:F100) -> 0 | G101: =-SUM(G87:G100) -> 0 | H101: =-SUM(H87:H100) -> 0
B103: Financing
B105: Financing costs
B106: Debt repayment | C106: =C168 -> 0 | D106: =D168 -> 32400 | E106: =E168 -> 32400 | F106: =F168 -> 32400 | G106: =G168 -> 32400 | H106: =H168 -> 32400
B108: Cash flow from financing | C108: =-SUM(C106:C106) -> 0 | D108: =-SUM(D106:D106) -> -32400 | E108: =-SUM(E106:E106) -> -32400 | F108: =-SUM(F106:F106) -> -32400 | G108: =-SUM(G106:G106) -> -32400 | H108: =-SUM(H106:H106) -> -32400
B110: Total cash flow
B112: Cash flow from operations | C112: =C83 -> 0 | D112: =D83 -> 37597.315 | E112: =E83 -> 52508.663 | F112: =F83 -> 67324.966 | G112: =G83 -> 94783.208 | H112: =H83 -> 128857.17
B113: Cash flow from investments | C113: =C101 -> -162000 | D113: =D101 -> 0 | E113: =E101 -> 0 | F113: =F101 -> 0 | G113: =G101 -> 0 | H113: =H101 -> 0
B114: Cash flow from financing | C114: =C108 -> 0 | D114: =D108 -> -32400 | E114: =E108 -> -32400 | F114: =F108 -> -32400 | G114: =G108 -> -32400 | H114: =H108 -> -32400 | I114: Terminal value
B115: Total cash flow | C115: =C112+C113+C114 -> -162000 | D115: =D112+D113+D114 -> 5197.3151 | E115: =E112+E113+E114 -> 20108.663 | F115: =F112+F113+F114 -> 34924.966 | G115: =G112+G113+G114 -> 62383.208 | H115: =H112+H113+H114 -> 96457.168 | I115: =H115*(1+C35)/(C34-C35) -> 2025600.5
B117: Cumulative cash flow | C117: =C115 -> -162000 | D117: =C117+D115 -> -156802.68 | E117: =D117+E115 -> -136694.02 | F117: =E117+F115 -> -101769.06 | G117: =F117+G115 -> -39385.848 | H117: =G117+H115 -> 57071.32 | I117: =I115+H117 -> 2082671.8
B141: Discounted cash flow (DCF) | C141: Entry | D141: Year 1 | E141: Year 2 | F141: Year 3 | G141: Year 4 | H141: Year 5 | I141: Exit
B143: Period | C143: =C13 -> 0 | D143: =D13 -> 1 | E143: =E13 -> 2 | F143: =F13 -> 3 | G143: =G13 -> 4 | H143: =H13 -> 5 | I143: =I13 -> 6
B144: Total cash flow | C144: =C115 -> -162000 | D144: =D115 -> 5197.3151 | E144: =E115 -> 20108.663 | F144: =F115 -> 34924.966 | G144: =G115 -> 62383.208 | H144: =H115 -> 96457.168 | I144: =I115 -> 2025600.5
B145: Present value of total cash flow | C145: =C144/((1+$C$34)^C143) -> -162000 | D145: =D144/((1+$C$34)^D143) -> 4724.8319 | E145: =E144/((1+$C$34)^E143) -> 16618.73 | F145: =F144/((1+$C$34)^F143) -> 26239.644 | G145: =G144/((1+$C$34)^G143) -> 42608.57 | H145: =H144/((1+$C$34)^H143) -> 59892.312 | I145: =I144/((1+$C$34)^I143) -> 1143398.7
B146: Cumulative present value of total cash flow | C146: =C145 -> -162000 | D146: =C146+D145 -> -157275.17 | E146: =D146+E145 -> -140656.44 | F146: =E146+F145 -> -114416.79 | G146: =F146+G145 -> -71808.224 | H146: =G146+H145 -> -11915.912 | I146: =H146+I145 -> 1131482.8
B148: Net present value (NPV): | C148: =NPV(C34,D144:I144)+C144 -> 1131482.8
B150: Internal rate of return: | C150: =IRR(C144:I144) -> 0.59458994
B152: Payback period | C152: {=ROUND(IFERROR(COUNTIF(D146:I146,"<"&0)+INDEX(D152:I152,,COUNTIF(D146:I146,"<"&0)+1),"> Nil"),2) &" years"} -> 5.99 years | D152: =IF(D146<0," - ",D146/D145) -> - | E152: =IF(E146<0," - ",E146/E145) -> - | F152: =IF(F146<0," - ",F146/F145) -> - | G152: =IF(G146<0," - ",G146/G145) -> - | H152: =IF(H146<0," - ",H146/H145) -> - | I152: =IF(I146<0," - ",I146/I145) -> 0.98957852
B154: Return on investment (ROI): | C154: =ABS(C148/SUM(C101:H101))-1 -> 5.9844616
B157: Supporting calculations | C157: Entry | D157: Year 1 | E157: Year 2 | F157: Year 3 | G157: Year 4 | H157: Year 5 | I157: Exit
B159: Depreciation schedule
B160: Property, plant & equipment (PPE) opening | C160: 0 | D160: =C163 -> 162000 | E160: =D163 -> 145800 | F160: =E163 -> 131220 | G160: =F163 -> 118098 | H160: =G163 -> 106288.2 | I160: =H163 -> 95659.38
B161: Plus capex/project investments | C161: =-C101 -> 162000 | D161: =-D101 -> 0 | E161: =-E101 -> 0 | F161: =-F101 -> 0 | G161: =-G101 -> 0 | H161: =-H101 -> 0
B162: Less depreciation | C162: 0 | D162: =D160*$C$19 -> 16200 | E162: =E160*$C$19 -> 14580 | F162: =F160*$C$19 -> 13122 | G162: =G160*$C$19 -> 11809.8 | H162: =H160*$C$19 -> 10628.82
B163: Property, plant & equipment (PPE) closing | C163: =C160+C161-C162 -> 162000 | D163: =D160+D161-D162 -> 145800 | E163: =E160+E161-E162 -> 131220 | F163: =F160+F161-F162 -> 118098 | G163: =G160+G161-G162 -> 106288.2 | H163: =H160+H161-H162 -> 95659.38
B165: Debt & interest schedule
...

Sheet Option 3
B2: Option 3: | C2: [Insert name of option e.g., High growth]
B4: Option 3: | C4: =C2 -> [Insert name of option e.g., High growth]
B5: Description: | C5: [Insert brief description of scenario]
B7: Assumptions | C7: Entry | D7: Year 1 | E7: Year 2 | F7: Year 3 | G7: Year 4 | H7: Year 5 | I7: Exit
B9: Business Case Timing
B10: Start Date | C10: 45778
B11: Fiscal Year Date | C11: 45838
B12: Date | C12: =C10 -> 45778 | D12: =DATE(YEAR($C$11)+D13,6,30) -> 46203 | E12: =DATE(YEAR($C$11)+E13,6,30) -> 46568 | F12: =DATE(YEAR($C$11)+F13,6,30) -> 46934 | G12: =DATE(YEAR($C$11)+G13,6,30) -> 47299 | H12: =DATE(YEAR($C$11)+H13,6,30) -> 47664 | I12: =DATE(YEAR($C$11)+I13,6,30) -> 48029
B13: Time periods | C13: 0 | D13: 1 | E13: =D13+1 -> 2 | F13: =E13+1 -> 3 | G13: =F13+1 -> 4 | H13: =G13+1 -> 5 | I13: =H13+1 -> 6
B14: Year fraction | D14: =YEARFRAC(C12,D12) -> 1.1638889 | E14: =YEARFRAC(D12,E12) -> 1 | F14: =YEARFRAC(E12,F12) -> 1 | G14: =YEARFRAC(F12,G12) -> 1 | H14: =YEARFRAC(G12,H12) -> 1
B16: Operations
B17: Cost of goods sold (% of revenue) | C17: 0.4
B18: Tax rate | C18: 0.22
B19: Depreciation & amortization | C19: 0.1
B21: Project investment
B22: Buffer on capex investments | C22: 0.2
B24: Working capital
B25: Accounts receivable (days) | C25: 30
B26: Inventory (days) | C26: 60
B27: Accounts payable (days) | C27: 30
B29: Financing
B30: Interest rate on debt (%) | C30: 0.1
B31: Yearly debt repayments (% of total debt) | C31: 0.2
B33: DCF Analysis
B34: Discount Rate | C34: 0.1
B35: Perpetual Growth Rate | C35: 0.05
B37: Business case | C37: Entry | D37: Year 1 | E37: Year 2 | F37: Year 3 | G37: Year 4 | H37: Year 5 | I37: Exit
B39: Operations
B41: Revenues
B42: New revenue generated | D42: 275000 | E42: 290000 | F42: 350000 | G42: 480000 | H42: 550000
B43: Cost of goods sold (COGS) | D43: =D42*$C$17 -> 110000 | E43: =E42*$C$17 -> 116000 | F43: =F42*$C$17 -> 140000 | G43: =G42*$C$17 -> 192000 | H43: =H42*$C$17 -> 220000
B44: Gross margin | C44: =(C42-C43) -> 0 | D44: =(D42-D43) -> 165000 | E44: =(E42-E43) -> 174000 | F44: =(F42-F43) -> 210000 | G44: =(G42-G43) -> 288000 | H44: =(H42-H43) -> 330000
B46: Cost savings
B47: Cost savings #1 | D47: 100000 | E47: 80000 | F47: 80000 | G47: 80000 | H47: 80000
B48: Cost savings #1 | D48: 0 | E48: 0 | F48: 0 | G48: 0 | H48: 0
B49: Total cost savings | C49: =SUM(C47:C48) -> 0 | D49: =SUM(D47:D48) -> 100000 | E49: =SUM(E47:E48) -> 80000 | F49: =SUM(F47:F48) -> 80000 | G49: =SUM(G47:G48) -> 80000 | H49: =SUM(H47:H48) -> 80000
B51: Ongoing project costs
B53: Operating expenses
B54: Ongoing cost #1 (e.g., salaries) | D54: 100000 | E54: =D54 -> 100000 | F54: =E54 -> 100000 | G54: =F54 -> 100000 | H54: =G54 -> 100000
B55: Ongoing cost #2 (e.g., personnel expenses) | D55: 25000 | E55: =D55 -> 25000 | F55: =E55 -> 25000 | G55: =F55 -> 25000 | H55: =G55 -> 25000
B56: Ongoing cost #3 (e.g., software licenses) | D56: 4000 | E56: =D56 -> 4000 | F56: =E56 -> 4000 | G56: =F56 -> 4000 | H56: =G56 -> 4000
B57: Ongoing cost #4 | D57: 1000 | E57: 1000 | F57: 1000 | G57: 1000 | H57: 1000
B58: Ongoing cost #5 | D58: 0 | E58: 0 | F58: 0 | G58: 0 | H58: 0
B60: Marketing and sales expenses
B61: Ongoing cost #6 (e.g., Meta) | D61: 10000 | E61: 10000 | F61: 10000 | G61: 10000 | H61: 10000
B62: Ongoing cost #7 | D62: 0 | E62: 0 | F62: 0 | G62: 0 | H62: 0
B63: Ongoing cost #8 | D63: 0 | E63: 0 | F63: 0 | G63: 0 | H63: 0
B64: Ongoing cost #9 | D64: 0 | E64: 0 | F64: 0 | G64: 0 | H64: 0
B65: Ongoing cost #10 | D65: 0 | E65: 0 | F65: 0 | G65: 0 | H65: 0
B67: Other expenses
B68: Ongoing cost #11 | D68: 0 | E68: 0 | F68: 0 | G68: 0 | H68: 0
B70: Total ongoing project costs | C70: =-SUM(C52:C69) -> 0 | D70: =-SUM(D52:D69) -> -140000 | E70: =-SUM(E52:E69) -> -140000 | F70: =-SUM(F52:F69) -> -140000 | G70: =-SUM(G52:G69) -> -140000 | H70: =-SUM(H52:H69) -> -140000
B72: Earnings before interest, tax, depreciation, amortization (EBITDA) | C72: =C44+C49+C70 -> 0 | D72: =D44+D49+D70 -> 125000 | E72: =E44+E49+E70 -> 114000 | F72: =F44+F49+F70 -> 150000 | G72: =G44+G49+G70 -> 228000 | H72: =H44+H49+H70 -> 270000
B74: Depreciation | C74: =C162 -> 0 | D74: =D162 -> 30600 | E74: =E162 -> 27540 | F74: =F162 -> 24786 | G74: =G162 -> 22307.4 | H74: =H162 -> 20076.66
B75: Interest | C75: =C171 -> 0 | D75: =D171 -> 30600 | E75: =E171 -> 24480 | F75: =F171 -> 18360 | G75: =G171 -> 12240 | H75: =H171 -> 6120
B76: Earnings before tax | C76: =C72-C74-C75 -> 0 | D76: =D72-D74-D75 -> 63800 | E76: =E72-E74-E75 -> 61980 | F76: =F72-F74-F75 -> 106854 | G76: =G72-G74-G75 -> 193452.6 | H76: =H72-H74-H75 -> 243803.34
B78: Tax | C78: =C76*$C$18 -> 0 | D78: =D76*$C$18 -> 14036 | E78: =E76*$C$18 -> 13635.6 | F78: =F76*$C$18 -> 23507.88 | G78: =G76*$C$18 -> 42559.572 | H78: =H76*$C$18 -> 53636.735
B79: Earnings after tax | C79: =C76-C78 -> 0 | D79: =D76-D78 -> 49764 | E79: =E76-E78 -> 48344.4 | F79: =F76-F78 -> 83346.12 | G79: =G76-G78 -> 150893.03 | H79: =H76-H78 -> 190166.61
B81: Plus: Depreciation and amortization | C81: =C74 -> 0 | D81: =D74 -> 30600 | E81: =E74 -> 27540 | F81: =F74 -> 24786 | G81: =G74 -> 22307.4 | H81: =H74 -> 20076.66
B82: Less: Changes in working capital | C82: =C178 -> 0 | D82: =D178 -> 26219.178 | E82: =E178 -> 1430.137 | F82: =F178 -> 5720.5479 | G82: =G178 -> 12394.521 | H82: =H178 -> 6673.9726
B83: Cash flow from operations | C83: =C79+C81-C82 -> 0 | D83: =D79+D81-D82 -> 54144.822 | E83: =E79+E81-E82 -> 74454.263 | F83: =F79+F81-F82 -> 102411.57 | G83: =G79+G81-G82 -> 160805.91 | H83: =H79+H81-H82 -> 203569.29
B85: Investments
B87: Capital expenditures
B88: Investment category #1 (e.g., production equipment) | C88: 200000 | D88: 0 | E88: 0 | F88: 0 | G88: 0 | H88: 0
B89: Investment category #2 (e.g., IT hardware) | C89: 25000 | D89: 0 | E89: 0 | F89: 0 | G89: 0 | H89: 0
B90: Investment category #3 | C90: 20000 | D90: 0 | E90: 0 | F90: 0 | G90: 0 | H90: 0
B91: Investment category #4 | C91: 0 | D91: 0 | E91: 0 | F91: 0 | G91: 0 | H91: 0
B92: Investment category #5 | C92: 0 | D92: 0 | E92: 0 | F92: 0 | G92: 0 | H92: 0
B94: Project expenses (one-time expenses)
B95: Expense #1 (e.g., prototype development) | C95: 10000 | D95: 0 | E95: 0 | F95: 0 | G95: 0 | H95: 0
B96: Expense #2 | C96: 0 | D96: 0 | E96: 0 | F96: 0 | G96: 0 | H96: 0
B97: Expense #3 | C97: 0 | D97: 0 | E97: 0 | F97: 0 | G97: 0 | H97: 0
B99: Buffer | C99: =$C$22*SUM(C88:C97) -> 51000 | D99: =$C$22*SUM(D88:D97) -> 0 | E99: =$C$22*SUM(E88:E97) -> 0 | F99: =$C$22*SUM(F88:F97) -> 0 | G99: =$C$22*SUM(G88:G97) -> 0 | H99: =$C$22*SUM(H88:H97) -> 0
B101: Cash flow from investments (Capex) | C101: =-SUM(C87:C100) -> -306000 | D101: =-SUM(D87:D100) -> 0 | E101: =-SUM(E87:E100) -> 0 | F101: =-SUM(F87:F100) -> 0 | G101: =-SUM(G87:G100) -> 0 | H101: =-SUM(H87:H100) -> 0
B103: Financing
B105: Financing costs
B106: Debt repayment | C106: =C168 -> 0 | D106: =D168 -> 61200 | E106: =E168 -> 61200 | F106: =F168 -> 61200 | G106: =G168 -> 61200 | H106: =H168 -> 61200
B108: Cash flow from financing | C108: =-SUM(C106:C106) -> 0 | D108: =-SUM(D106:D106) -> -61200 | E108: =-SUM(E106:E106) -> -61200 | F108: =-SUM(F106:F106) -> -61200 | G108: =-SUM(G106:G106) -> -61200 | H108: =-SUM(H106:H106) -> -61200
B110: Total cash flow
B112: Cash flow from operations | C112: =C83 -> 0 | D112: =D83 -> 54144.822 | E112: =E83 -> 74454.263 | F112: =F83 -> 102411.57 | G112: =G83 -> 160805.91 | H112: =H83 -> 203569.29
B113: Cash flow from investments | C113: =C101 -> -306000 | D113: =D101 -> 0 | E113: =E101 -> 0 | F113: =F101 -> 0 | G113: =G101 -> 0 | H113: =H101 -> 0
B114: Cash flow from financing | C114: =C108 -> 0 | D114: =D108 -> -61200 | E114: =E108 -> -61200 | F114: =F108 -> -61200 | G114: =G108 -> -61200 | H114: =H108 -> -61200 | I114: Terminal value
B115: Total cash flow | C115: =C112+C113+C114 -> -306000 | D115: =D112+D113+D114 -> -7055.1781 | E115: =E112+E113+E114 -> 13254.263 | F115: =F112+F113+F114 -> 41211.572 | G115: =G112+G113+G114 -> 99605.907 | H115: =H112+H113+H114 -> 142369.29 | I115: =H115*(1+C35)/(C34-C35) -> 2989755.1
B117: Cumulative cash flow | C117: =C115 -> -306000 | D117: =C117+D115 -> -313055.18 | E117: =D117+E115 -> -299800.92 | F117: =E117+F115 -> -258589.34 | G117: =F117+G115 -> -158983.44 | H117: =G117+H115 -> -16614.143 | I117: =I115+H117 -> 2973141
B141: Discounted cash flow (DCF) | C141: Entry | D141: Year 1 | E141: Year 2 | F141: Year 3 | G141: Year 4 | H141: Year 5 | I141: Exit
B143: Period | C143: =C13 -> 0 | D143: =D13 -> 1 | E143: =E13 -> 2 | F143: =F13 -> 3 | G143: =G13 -> 4 | H143: =H13 -> 5 | I143: =I13 -> 6
B144: Total cash flow | C144: =C115 -> -306000 | D144: =D115 -> -7055.1781 | E144: =E115 -> 13254.263 | F144: =F115 -> 41211.572 | G144: =G115 -> 99605.907 | H144: =H115 -> 142369.29 | I144: =I115 -> 2989755.1
B145: Present value of total cash flow | C145: =C144/((1+$C$34)^C143) -> -306000 | D145: =D144/((1+$C$34)^D143) -> -6413.7983 | E145: =E144/((1+$C$34)^E143) -> 10953.936 | F145: =F144/((1+$C$34)^F143) -> 30962.864 | G145: =G144/((1+$C$34)^G143) -> 68032.175 | H145: =H144/((1+$C$34)^H143) -> 88400.13 | I145: =I144/((1+$C$34)^I143) -> 1687638.8
B146: Cumulative present value of total cash flow | C146: =C145 -> -306000 | D146: =C146+D145 -> -312413.8 | E146: =D146+E145 -> -301459.86 | F146: =E146+F145 -> -270497 | G146: =F146+G145 -> -202464.82 | H146: =G146+H145 -> -114064.69 | I146: =H146+I145 -> 1573574.1
B148: Net present value (NPV): | C148: =NPV(C34,D144:I144)+C144 -> 1573574.1
B150: Internal rate of return: | C150: =IRR(C144:I144) -> 0.50706001
B152: Payback period | C152: {=ROUND(IFERROR(COUNTIF(D146:I146,"<"&0)+INDEX(D152:I152,,COUNTIF(D146:I146,"<"&0)+1),"> Nil"),2) &" years"} -> 5.93 years | D152: =IF(D146<0," - ",D146/D145) -> - | E152: =IF(E146<0," - ",E146/E145) -> - | F152: =IF(F146<0," - ",F146/F145) -> - | G152: =IF(G146<0," - ",G146/G145) -> - | H152: =IF(H146<0," - ",H146/H145) -> - | I152: =IF(I146<0," - ",I146/I145) -> 0.93241167
B154: Return on investment (ROI): | C154: =ABS(C148/SUM(C101:H101))-1 -> 4.1423992
B157: Supporting calculations | C157: Entry | D157: Year 1 | E157: Year 2 | F157: Year 3 | G157: Year 4 | H157: Year 5 | I157: Exit
B159: Depreciation schedule
B160: Property, plant & equipment (PPE) opening | C160: 0 | D160: =C163 -> 306000 | E160: =D163 -> 275400 | F160: =E163 -> 247860 | G160: =F163 -> 223074 | H160: =G163 -> 200766.6 | I160: =H163 -> 180689.94
B161: Plus capex/project investments | C161: =-C101 -> 306000 | D161: =-D101 -> 0 | E161: =-E101 -> 0 | F161: =-F101 -> 0 | G161: =-G101 -> 0 | H161: =-H101 -> 0
B162: Less depreciation | C162: 0 | D162: =D160*$C$19 -> 30600 | E162: =E160*$C$19 -> 27540 | F162: =F160*$C$19 -> 24786 | G162: =G160*$C$19 -> 22307.4 | H162: =H160*$C$19 -> 20076.66
B163: Property, plant & equipment (PPE) closing | C163: =C160+C161-C162 -> 306000 | D163: =D160+D161-D162 -> 275400 | E163: =E160+E161-E162 -> 247860 | F163: =F160+F161-F162 -> 223074 | G163: =G160+G161-G162 -> 200766.6 | H163: =H160+H161-H162 -> 180689.94
B165: Debt & interest schedule
...
